{
 "topics": [
  {
   "slug": "scan-atom",
   "title": "สแกนเครื่องเข้าระบบ ATOM",
   "subtitle": "ใช้ตอนรับเครื่องใหม่มาผ่อน ต้องเอาเข้าระบบ MDM ก่อนส่งมอบลูกค้า",
   "icon": "📲",
   "summary": "คู่มือขั้นตอนเอาเครื่อง iPhone ที่ลูกค้าจะผ่อนเข้าระบบ MDM ด้วยแอป Apple Configurator บนเครื่องของร้านค้า โดยสแกน \"ฝุ่น\" (ลายจุด) ที่ขึ้นบนเครื่องลูกค้า แล้วลงทะเบียนรหัสร้านค้า ชื่อ-เบอร์ลูกค้า เครื่องจะถูกผูกเข้าองค์กร ATOM TECHWORLD TECHNOLOGY COMPANY LIMITED และบริการจัดการอุปกรณ์ \"Marena\" ใน Apple Business Manager ใช้โดยพนักงานหน้าร้านตอนทำสัญญาผ่อนเครื่องใหม่ ท้ายคู่มือมีวิธีเช็คว่าเครื่องเข้าระบบสมบูรณ์แล้วหรือยัง",
   "keywords": [
    "สแกนเครื่อง",
    "สแกนฝุ่น",
    "เอาเครื่องเข้าระบบ",
    "Apple Configurator",
    "atom",
    "ATOM TECHWORLD",
    "MDM",
    "Marena",
    "Apple Business Manager",
    "ABM",
    "ลงทะเบียนอุปกรณ์",
    "รหัสร้านค้า",
    "ล้างเครื่อง",
    "ตั้งค่าโดยไม่ต้องใช้อุปกรณ์อื่น",
    "เครื่องใหม่ผ่อน",
    "enroll",
    "scan",
    "เลือกเซิร์ฟเวอร์ MDM",
    "ระบุเฉพาะ",
    "ใช้บัญชี Apple อื่น",
    "บริการหาตำแหน่งที่ตั้ง",
    "เครื่องถูกกำกับดูแล",
    "supervised",
    "Atomtech"
   ],
   "pages": [
    {
     "n": 1,
     "caption": "โหลดแอป Apple Configurator จาก App Store ลงในเครื่องของร้านค้า (เครื่องที่ใช้สแกน) แล้วเอา USERNAME ที่ได้รับไปล็อกอินที่หน้า \"ลงชื่อเข้า\" ในช่องที่อยู่อีเมล"
    },
    {
     "n": 2,
     "caption": "(1) ใส่ USERNAME แล้วจะมีป๊อปอัปเด้งขึ้น ให้กด \"ใช้บัญชี Apple อื่น\" (ช่องล่าง) ไม่ใช่ \"ลงชื่อเข้า\" → (2) หน้า \"ต้องลงชื่อเข้าด้วยบัญชี Apple\" ใส่บัญชีแล้วกดลงชื่อเข้า → (3) หน้า \"บัญชี Apple สำหรับองค์กรของคุณ\" กด \"ดำเนินการต่อ\""
    },
    {
     "n": 3,
     "caption": "(1) ในแอปกดปุ่มเฟืองมุมล่างซ้าย → (2) หัวข้อ \"การกำหนดค่าเครือข่าย\" เลือก \"แชร์ Wi-Fi\" (เครือข่าย Atomtech) และหัวข้อ \"การกำหนดเซิร์ฟเวอร์ MDM\" เปลี่ยนจาก \"ไม่มี\" เป็น \"ระบุเฉพาะ\" → (3) หน้า \"เลือกเซิร์ฟเวอร์ MDM\" เลือกชื่อ \"MDM\" (ไม่ใช่ ICON FRUIT)"
    },
    {
     "n": 4,
     "caption": "ฝั่งเครื่องลูกค้า: เอาเครื่องที่จะผ่อนมาล้างข้อมูลจนขึ้นหน้า \"สวัสดี\" → หน้า \"ตั้งค่า iPhone อย่างรวดเร็ว\" กดปุ่มล่างสุด \"ตั้งค่าโดยไม่ต้องใช้อุปกรณ์อื่น\" → พอมาถึงหน้า \"เลือกเครือข่าย Wi-Fi\" ห้ามเชื่อมต่อไวไฟ ให้ไปทำการสแกนฝุ่นตามหน้าถัดไป"
    },
    {
     "n": 5,
     "caption": "(1) เครื่องของร้านเปิดหน้าสแกน จะขึ้น \"กำลังค้นหาอุปกรณ์เพื่อเพิ่ม...\" → (2) เครื่องที่จะผ่อนขึ้นหน้า \"เพิ่ม iPhone เครื่องนี้ไปยังองค์กรของคุณ\" พร้อมลายฝุ่นให้สแกน → (3) นำเครื่องของร้านไปส่องสแกนลายฝุ่นบนเครื่องลูกค้าให้อยู่ในกรอบวงกลม"
    },
    {
     "n": 6,
     "caption": "(1) เข้าระบบสำเร็จขึ้น \"เพิ่ม iPhone แล้ว\" — เครื่องถูกเพิ่มไปยัง ATOM TECHWORLD TECHNOLOGY COMPANY LIMITED และกำหนดให้ใช้บริการจัดการอุปกรณ์ \"Marena\" ใน Apple Business Manager ให้กดปุ่ม \"ลบข้อมูล iPhone\" → (2) หน้า \"การจัดการอุปกรณ์\" กดปุ่มน้ำเงิน \"ลงทะเบียน iPhone เครื่องนี้\" → (3) เข้าหน้า \"การลงทะเบียนอุปกรณ์\" กรอกข้อมูลตามหน้าถัดไป"
    },
    {
     "n": 7,
     "caption": "กรอกข้อมูลในหน้า \"การลงทะเบียนอุปกรณ์\": ช่อง \"รหัสร้านค้า/หมายเลขบัญชี\" ใส่รหัสที่แอดมินสร้างให้, ช่อง \"ชื่อลูกค้า\" ใส่ชื่อ-นามสกุลลูกค้า, ช่อง \"โทรศัพท์ของลูกค้า\" ใส่เบอร์โทรลูกค้า → กด \"ลงทะเบียนตอนนี้\" → หน้า \"บริการหาตำแหน่งที่ตั้ง\" กดปุ่มน้ำเงิน \"เปิดใช้บริการหาตำแหน่งที่ตั้ง\" (ไม่ใช่ \"ตั้งค่าในภายหลัง\")"
    },
    {
     "n": 8,
     "caption": "วิธีเช็คว่าเครื่องเข้าระบบสมบูรณ์ มี 2 จุด: (ซ้าย) หน้า \"การตั้งค่า\" ด้านบนสุดต้องขึ้น \"iPhone เครื่องนี้ถูกกำกับดูแลและจัดการโดย ATOM TECHWORLD TECHNOLOGY COMPANY LIMITED\" และ (ขวา) ที่หน้า \"ถ่ายโอนหรือรีเซ็ต iPhone\" ต้องกด \"ลบข้อมูลและการตั้งค่าทั้งหมด\" ไม่ได้ (ล้างเครื่องไม่ได้)"
    }
   ],
   "steps": [
    {
     "title": "โหลดแอปและล็อกอินในเครื่องของร้าน",
     "detail": "โหลดแอป Apple Configurator จาก App Store ลงในเครื่องของร้านค้า (เครื่องที่จะใช้สแกน) จากนั้นเอา USERNAME ที่ได้รับมาใส่ที่หน้า \"ลงชื่อเข้า\"",
     "page": 1
    },
    {
     "title": "ล็อกอินด้วย \"ใช้บัญชี Apple อื่น\"",
     "detail": "ใส่ USERNAME แล้วป๊อปอัปจะเด้งขึ้น ให้กด \"ใช้บัญชี Apple อื่น\" → ลงชื่อเข้าด้วยบัญชี Apple ที่ได้รับ → พอขึ้นหน้า \"บัญชี Apple สำหรับองค์กรของคุณ\" กด \"ดำเนินการต่อ\"",
     "page": 2
    },
    {
     "title": "ตั้งค่าเซิร์ฟเวอร์ MDM ในแอป",
     "detail": "กดปุ่มเฟืองมุมล่างซ้าย → หัวข้อ \"การกำหนดค่าเครือข่าย\" เลือก \"แชร์ Wi-Fi\" (เครือข่าย Atomtech) → หัวข้อ \"การกำหนดเซิร์ฟเวอร์ MDM\" เลือก \"ระบุเฉพาะ\" → หน้า \"เลือกเซิร์ฟเวอร์ MDM\" เลือกชื่อ \"MDM\"",
     "page": 3
    },
    {
     "title": "เตรียมเครื่องลูกค้า",
     "detail": "เอาเครื่องที่จะผ่อนมาล้างข้อมูลจนขึ้นหน้า \"สวัสดี\" → ที่หน้า \"ตั้งค่า iPhone อย่างรวดเร็ว\" กด \"ตั้งค่าโดยไม่ต้องใช้อุปกรณ์อื่น\" ที่ปุ่มล่างสุด → พอถึงหน้า \"เลือกเครือข่าย Wi-Fi\" ห้ามเชื่อมต่อไวไฟ ให้ไปสแกนฝุ่นแทน",
     "page": 4
    },
    {
     "title": "สแกนฝุ่น",
     "detail": "เปิดหน้าสแกนในเครื่องของร้าน (จะขึ้น \"กำลังค้นหาอุปกรณ์เพื่อเพิ่ม...\") → เครื่องลูกค้าจะขึ้นหน้า \"เพิ่ม iPhone เครื่องนี้ไปยังองค์กรของคุณ\" พร้อมลายฝุ่น → นำเครื่องของร้านไปส่องลายฝุ่นให้อยู่ในกรอบวงกลมจนสแกนติด",
     "page": 5
    },
    {
     "title": "ลบข้อมูลและลงทะเบียนเครื่อง",
     "detail": "สำเร็จจะขึ้น \"เพิ่ม iPhone แล้ว\" (ผูกกับ ATOM TECHWORLD และบริการจัดการอุปกรณ์ \"Marena\") ให้กด \"ลบข้อมูล iPhone\" → หน้า \"การจัดการอุปกรณ์\" กด \"ลงทะเบียน iPhone เครื่องนี้\" → เข้าหน้า \"การลงทะเบียนอุปกรณ์\"",
     "page": 6
    },
    {
     "title": "กรอกข้อมูลลงทะเบียนและเปิดตำแหน่ง",
     "detail": "กรอก \"รหัสร้านค้า/หมายเลขบัญชี\" ที่แอดมินสร้างให้, \"ชื่อลูกค้า\" (ชื่อ-นามสกุล), \"โทรศัพท์ของลูกค้า\" → กด \"ลงทะเบียนตอนนี้\" → กด \"เปิดใช้บริการหาตำแหน่งที่ตั้ง\"",
     "page": 7
    },
    {
     "title": "เช็คว่าเครื่องเข้าระบบสมบูรณ์",
     "detail": "เข้า \"การตั้งค่า\" ด้านบนสุดต้องขึ้นว่า iPhone เครื่องนี้ถูกกำกับดูแลและจัดการโดย ATOM TECHWORLD TECHNOLOGY COMPANY LIMITED และลองเข้าหน้า \"ถ่ายโอนหรือรีเซ็ต iPhone\" ต้องกด \"ลบข้อมูลและการตั้งค่าทั้งหมด\" ไม่ได้",
     "page": 8
    }
   ],
   "warnings": [
    "ห้ามเชื่อมต่อ Wi-Fi ที่เครื่องลูกค้าตอนถึงหน้า \"เลือกเครือข่าย Wi-Fi\" ต้องข้ามไปสแกนฝุ่นแทน (รูป 4)",
    "แอป Apple Configurator ต้องลงในเครื่องของร้านค้าเท่านั้น ไม่ใช่เครื่องลูกค้าที่จะผ่อน (รูป 1)",
    "ตอนล็อกอินต้องกด \"ใช้บัญชี Apple อื่น\" ในป๊อปอัป ไม่ใช่กด \"ลงชื่อเข้า\" ที่อยู่เหนือมัน (รูป 2)",
    "หัวข้อ \"การกำหนดเซิร์ฟเวอร์ MDM\" ค่าเริ่มต้นติ๊ก \"ไม่มี\" อยู่ ต้องเปลี่ยนเป็น \"ระบุเฉพาะ\" แล้วเลือกเซิร์ฟเวอร์ \"MDM\" ระวังกดผิดเป็น ICON FRUIT (รูป 3)",
    "หน้า \"การจัดการอุปกรณ์\" ปุ่ม \"เอา iPhone ออกจากองค์กร\" อยู่ใต้ปุ่ม \"ลงทะเบียน iPhone เครื่องนี้\" พอดี ระวังกดผิด (รูป 6)",
    "รหัสร้านค้าต้องใช้ที่แอดมินสร้างให้เท่านั้น กรอกที่ช่อง \"รหัสร้านค้า/หมายเลขบัญชี\" (รูป 7)",
    "หลังลงทะเบียนต้องกด \"เปิดใช้บริการหาตำแหน่งที่ตั้ง\" อย่ากด \"ตั้งค่าในภายหลัง\" ที่อยู่ข้างล่าง (รูป 7)",
    "ถ้าการตั้งค่าไม่ขึ้นข้อความ ATOM TECHWORLD หรือยังกด \"ลบข้อมูลและการตั้งค่าทั้งหมด\" ได้ แปลว่าเข้าระบบไม่สมบูรณ์ (รูป 8)"
   ]
  },
  {
   "slug": "mass-mdm",
   "title": "คู่มือการทำงานของแมส",
   "subtitle": "ใช้ตอนรับเคสจาก Admin ออกไปสแกนเครื่อง ทำสัญญา และถ่ายรูปหน้างาน",
   "icon": "🛵",
   "summary": "คู่มือการทำงานภาคสนามของแมส (Messenger) ระบบ MARENA MDM แบ่งเป็น 5 ขั้นตอน ตั้งแต่รับเคสจาก Admin เช็คอุปกรณ์ โทรคอนเฟิร์ม เดินทางไปสแกนเครื่องด้วย Apple Configurator ถ่ายรูป 17 ใบ ให้ลูกค้าอ่านและเซ็นสัญญาออนไลน์ จนถึงแจ้ง Admin ปิดเคส ท้ายเล่มมีตารางสรุปอุปกรณ์ที่ต้องเตรียม 7 รายการ และตารางข้อควรระวัง 6 สถานการณ์พร้อมวิธีแก้หน้างาน ใช้สำหรับแมสที่ต้องออกไปพบลูกค้านอกร้าน",
   "keywords": [
    "แมส",
    "messenger",
    "รับเคสจาก Admin",
    "ค่าแมส",
    "สแกนเครื่อง",
    "Apple Configurator",
    "enrollment",
    "ทำสัญญา",
    "เซ็นออนไลน์",
    "ถ่ายรูป 17 รูป",
    "รอบเครื่อง",
    "บัตรประชาชน",
    "ขอรหัส Admin",
    "MARENA MDM",
    "ปิดเคส"
   ],
   "pages": [
    {
     "n": 1,
     "caption": "หน้าปก MARENA MDM — คู่มือการทำงาน สำหรับแมส (Messenger) ภาคสนาม สรุป 5 ขั้นตอน รับเคส → ทำสัญญา → จบงาน (เอกสารฝึกอบรม ปรับปรุง พ.ค. 2026)"
    },
    {
     "n": 2,
     "caption": "สารบัญ 7 หัวข้อ — รับเคสและคำนวณค่าแมส, ตรวจเช็คอุปกรณ์, โทรคอนเฟิร์ม/เดินทาง/ขอรหัส/สแกนเครื่อง, ถ่ายรูป+อ่านสัญญา+เซ็นออนไลน์ (17 รูป), แจ้ง Admin รอจบงาน, สรุปอุปกรณ์ที่ต้องเตรียม และข้อควรระวังพร้อมวิธีแก้ปัญหา"
    },
    {
     "n": 3,
     "caption": "ขั้นตอนที่ 1 รับเคสจาก Admin — Admin ส่ง Location ลูกค้าเข้ากลุ่ม แมสเปิด Google Maps คำนวณระยะทาง เวลาเดินทาง และค่าแมส แล้วตอบกลับให้ครบ 3 ตัวเลข พร้อมตัวอย่างแชทกลุ่ม LINE ที่ Admin แจ้งข้อมูลลูกค้าครบ (ชื่อ เบอร์ Location นัดเวลา รุ่นเครื่อง ยอดสัญญา) และแมสตอบ \"รับเคส\" + แจ้งสถานะพร้อมออก"
    },
    {
     "n": 4,
     "caption": "ขั้นตอนที่ 2 ตรวจเช็คอุปกรณ์ 3 ข้อก่อนออกเดินทาง (แบต >50%, อินเตอร์เน็ต, แอป Apple Configurator) และขั้นตอนที่ 3 โทรคอนเฟิร์ม + เมื่อถึงสถานที่เช็คสภาพเครื่อง + ขอรหัสจาก Admin + สแกนเครื่องลงทะเบียน จนระบบขึ้นสถานะสีเขียว"
    },
    {
     "n": 5,
     "caption": "ขั้นตอนที่ 4 ถ่ายรูปเครื่อง + ถ่ายบัตรประชาชนคู่ลูกค้า + ให้ลูกค้าอ่านสัญญาและเซ็นออนไลน์ + ถ่ายรูปลูกค้าคู่สัญญา พร้อมกล่องเตือน 3 รูปที่ขาดไม่ได้ และหมายเหตุ PDPA ว่ารูปตัวอย่างในคู่มือเบลอไว้ แต่งานจริงต้องถ่ายชัด"
    },
    {
     "n": 6,
     "caption": "ตัวอย่างรูปจริง กลุ่ม A บัตรประชาชน + ลูกค้า 4 รูป (A1 บัตร ปชช, A2 ลูกค้า+เครื่อง, A3 บัตร+เครื่องวางคู่กัน, A4 ลูกค้าถือบัตรหันหน้า) และกลุ่ม B รอบเครื่อง 6 ด้าน + Lock Screen (B1 ด้านหน้า, B2 ด้านหลัง, B3 ข้างซ้าย-ปุ่มเสียง, B4 ข้างขวา-ปุ่มเปิดปิด, B5 ด้านบน, B6 ด้านล่าง-ช่องชาร์จ)"
    },
    {
     "n": 7,
     "caption": "ตัวอย่างรูปจริง กลุ่ม C หน้าจอข้อมูลเครื่อง 4 รูป (C1 หน้า Settings เห็น Apple ID, C2 เกี่ยวกับ-รุ่น/iOS/Serial, C3 SIM/IMEI, C4 แบตเตอรี่-% สุขภาพ+รอบชาร์จ) และกลุ่ม D สัญญา 3 รูป (D1 หน้าแรกสัญญา, D2 หน้าที่เซ็นแล้ว, D3 ตารางค่าความเสียหาย/เงื่อนไขการเช่า) — รวม 17 รูป = A(4)+B(6)+C(4)+D(3) ส่งทั้งหมดในกลุ่ม Admin"
    },
    {
     "n": 8,
     "caption": "ขั้นตอนที่ 5 แจ้ง Admin รอจบงาน — ส่งรูปทั้งหมดในกลุ่ม Admin แจ้ง \"งานเสร็จเรียบร้อย\" รอ Admin ตรวจสอบและคอนเฟิร์มปิดเคส กล่าวขอบคุณลูกค้าก่อนเดินทางกลับ แล้วรอรับเคสถัดไป"
    },
    {
     "n": 9,
     "caption": "ตารางสรุปอุปกรณ์และข้อมูลที่ต้องเตรียม 7 รายการ (อุปกรณ์, เครือข่าย, แอป, ข้อมูลลูกค้า, รหัส, สัญญา, รูปที่ต้องถ่าย) และตารางข้อควรระวัง 6 สถานการณ์พร้อมวิธีแก้"
    },
    {
     "n": 10,
     "caption": "หน้าปิดท้าย MARENA MDM — คู่มือการทำงานของแมส (Messenger) ภาคสนาม, Atom Tech © 2026 สำหรับใช้ภายในองค์กรเท่านั้น"
    }
   ],
   "steps": [
    {
     "title": "รับเคสจาก Admin และคำนวณค่าแมส",
     "detail": "Admin ส่ง Location ของลูกค้าเข้ากลุ่ม (พร้อมชื่อ เบอร์โทร เวลานัด รุ่นเครื่อง และยอดสัญญา) หน้าที่ของแมสคือเปิด Google Maps หรือแอปนำทาง คำนวณระยะทาง เวลาเดินทางโดยประมาณ (รวมเผื่อรถติด) และค่าแมสตามอัตราที่กำหนด แล้วแจ้งข้อมูลทั้งหมดกลับเข้ากลุ่ม Admin เคล็ดลับคือตอบให้เร็วและชัดเจน บอกครบ 3 ตัวเลข (ระยะทาง + เวลา + ค่าแมส) พร้อมแจ้งสถานะพร้อมออก",
     "page": 3
    },
    {
     "title": "ตรวจเช็คอุปกรณ์ก่อนออกเดินทาง",
     "detail": "เช็คให้ครบ 3 ข้อก่อนออกจากร้าน — 2.1 แบตเตอรี่มากกว่า 50% หากต่ำกว่าให้ชาร์จก่อนหรือพก Power Bank ไปด้วย, 2.2 ทดสอบอินเตอร์เน็ตว่าใช้งานได้ปกติ (เปิดเว็บ/ดูวิดีโอ) เพราะต้องใช้ตอนสแกนเครื่อง, 2.3 เปิดแอป Apple Configurator ขึ้นมาเช็คว่าทำงานได้ปกติ ไม่ค้าง ไม่ต้องอัปเดต",
     "page": 4
    },
    {
     "title": "โทรคอนเฟิร์ม + เดินทาง + ขอรหัส + สแกนเครื่อง",
     "detail": "3.1 โทรหาลูกค้าทุกครั้งก่อนออกเดินทาง เพื่อยืนยันว่ายังพร้อมและอยู่ในสถานที่นัดหมาย 3.2 เมื่อถึงสถานที่ ทักทายลูกค้าอย่างสุภาพ แนะนำตัว และเช็คสภาพเครื่องลูกค้าว่ามีรอย/แตก/บุบที่ใดบ้าง 3.3 แจ้ง Admin ในกลุ่มขอ USERNAME/รหัส สำหรับ Apple Configurator แล้วเลือก Wi-Fi ของลูกค้า กด Specify เซิร์ฟเวอร์ MDM 3.4 สแกนเครื่องด้วย Apple Configurator เริ่มกระบวนการ Enrollment และลงทะเบียน iPhone กรอกข้อมูลลูกค้า (รหัสร้าน, ชื่อลูกค้า, เบอร์โทร) สแกนสำเร็จ = ระบบขึ้นสถานะสีเขียว เครื่องจะ Wipe ไม่ได้",
     "page": 4
    },
    {
     "title": "ถ่ายรูป + อ่านสัญญา + เซ็นออนไลน์ (17 รูป)",
     "detail": "4.1 ถ่ายรูปมือถือรอบเครื่อง (หน้า หลัง ข้าง ขอบ) ให้เห็นสภาพชัดเจน และถ่ายหน้าจอข้อมูลเครื่อง (รุ่น, Serial Number, iOS, แบต) 4.2 ถ่ายบัตรประชาชนคู่กับลูกค้า โดยลูกค้าถือบัตรหันหน้าเข้ากล้อง ให้เห็นใบหน้าลูกค้าและรายละเอียดบนบัตรชัดเจน 4.3 ส่งสัญญาให้ลูกค้าอ่านก่อน ทำความเข้าใจเงื่อนไข ตอบข้อสงสัยให้เคลียร์ แล้วให้เซ็นออนไลน์ผ่านระบบ 4.4 ถ่ายรูปลูกค้าถือสัญญาที่เซ็นแล้วเก็บเป็นหลักฐาน รวมทั้งหมด 17 รูป — กลุ่ม A บัตร+ลูกค้า 4 รูป, กลุ่ม B รอบเครื่อง 6 ด้าน, กลุ่ม C หน้าจอ Settings 4 รูป, กลุ่ม D สัญญา 3 รูป",
     "page": 5
    },
    {
     "title": "แจ้ง Admin รอจบงาน",
     "detail": "เมื่อทำสัญญาเสร็จเรียบร้อยแล้ว ส่งรูปถ่ายทั้งหมดในกลุ่ม Admin แจ้ง Admin ว่า \"งานเสร็จเรียบร้อย\" รอ Admin ตรวจสอบความถูกต้องและคอนเฟิร์มปิดเคส แล้วกล่าวขอบคุณลูกค้าก่อนเดินทางกลับ จบงานแล้วรอรับเคสถัดไป",
     "page": 8
    }
   ],
   "warnings": [
    "ถ้าอุปกรณ์ข้อใดข้อหนึ่งไม่พร้อม (แบต/เน็ต/แอป) ห้ามออกงานเด็ดขาด เพราะจะทำงานต่อไม่ได้และเสียเวลาลูกค้า",
    "3 รูปนี้ขาดไม่ได้เด็ดขาด — 1) รอบเครื่อง 2) บัตร ปชช + ลูกค้า 3) ลูกค้า + สัญญา",
    "ต้องโทรหาลูกค้าทุกครั้งก่อนออกเดินทาง เพื่อยืนยันว่ายังพร้อมและอยู่ในสถานที่นัดหมาย",
    "รูปตัวอย่างในคู่มือถูกเบลอใบหน้าและข้อมูลส่วนตัวเพื่อปกป้อง PDPA แต่เวลาทำงานจริงให้ถ่ายชัดเจน ไม่ต้องเบลอ",
    "แบตเตอรี่ใกล้หมดระหว่างทำงาน → ใช้ Power Bank ที่เตรียมมา อย่ารอจนปิดเครื่อง",
    "อินเตอร์เน็ตช้า/ไม่เสถียร → เปิดฮอตสปอตจากมือถือสำรอง หรือใช้ Wi-Fi ลูกค้า",
    "Configurator ค้าง/Error → ปิด-เปิดแอปใหม่ แจ้ง Admin ทันทีถ้ายังไม่หาย",
    "เครื่องลูกค้าชำรุดก่อนสแกน → ถ่ายรูปบันทึกไว้ แจ้ง Admin ก่อนดำเนินการต่อ",
    "ลูกค้าไม่อยู่ตามนัด → โทรซ้ำ 2-3 ครั้ง รอ 15 นาที แล้วแจ้ง Admin",
    "ลูกค้าไม่ยอมเซ็นสัญญา → หยุดการดำเนินการ แจ้ง Admin ทันที"
   ]
  },
  {
   "slug": "mdm-agent",
   "title": "คู่มือ MDM Agent",
   "subtitle": "ใช้ตอนออกไปรับเคสลูกค้าออนไลน์ และเอาเครื่องลูกค้าเข้าระบบ MDM ด้วยแอป Configurator",
   "icon": "📲",
   "summary": "คู่มือสำหรับเอเจนต์ที่ออกไปรับเคสลูกค้านอกร้าน แบ่งเป็น 2 ส่วน คือวิธีเอาเครื่องเข้าระบบ MDM ผ่านแอป Configurator (ลงชื่อเข้าด้วยบัญชีองค์กร ตั้งค่าแชร์ Wi-Fi และเซิร์ฟเวอร์ MDM แล้วสแกนลงทะเบียนเครื่อง) และมาตรฐานการรับ/ส่งเคสออนไลน์ (เงื่อนไขรับเครื่อง ตารางราคา วิธีถ่ายรูปเครื่องและบัตรประชาชน และการเซ็นสัญญา) ใช้กับเครื่อง iPhone ที่ลูกค้าเอามารีไฟแนนซ์ผ่อนกับร้าน",
   "keywords": [
    "mdm agent",
    "configurator",
    "เอาเครื่องเข้าระบบ",
    "ลงทะเบียนเครื่อง enroll",
    "เซิร์ฟเวอร์ mdm",
    "ระบุเฉพาะ",
    "ใช้บัญชี Apple อื่น",
    "รับเคสออนไลน์",
    "ส่งเคสลูกค้าออนไลน์",
    "ตารางราคารีไฟแนนซ์",
    "สุขภาพแบตเตอรี่ รอบชาร์จ",
    "TH/A ZP/A",
    "เซ็นสัญญา",
    "ผู้ใช้ไม่ได้รับอนุญาต",
    "ติดตั้งโปรไฟล์ไม่สำเร็จ"
   ],
   "pages": [
    {
     "n": 1,
     "caption": "ไอคอนแอป Configurator บนหน้าจอเครื่องเอเจนต์"
    },
    {
     "n": 2,
     "caption": "หน้า \"ลงชื่อเข้า\" ของ Configurator — ช่อง \"ที่อยู่อีเมล\" ให้กรอกเมลที่ใช้ลงทะเบียน mmdl@zxcv.marenatech.com แล้วกด \"ดำเนินการต่อ\""
    },
    {
     "n": 3,
     "caption": "เด้งถามว่าจะใช้บัญชี Apple ที่ค้างอยู่ในเครื่องสำหรับ iCloud หรือไม่ ให้กด \"ใช้บัญชี Apple อื่น\" (กรอบแดง) ไม่ใช่ \"ลงชื่อเข้า\""
    },
    {
     "n": 4,
     "caption": "หน้า \"ต้องลงชื่อเข้าด้วยบัญชี Apple\" — ช่องอีเมลขึ้น mmdl@zxcv.marenatech.com อยู่แล้ว ให้กดปุ่ม \"ลงชื่อเข้า\" (กรอบแดง)"
    },
    {
     "n": 5,
     "caption": "หน้า \"บัญชี Apple สำหรับองค์กรของคุณ\" — ดำเนินการต่อไปยัง https://mmdl.mdmultra.com เพื่อลงชื่อเข้าบัญชี I CON FRUIT AND FOOD LIMITED PARTNERSHIP กด \"ดำเนินการต่อ\" (กรอบแดง)"
    },
    {
     "n": 6,
     "caption": "หน้าสแกน \"กำลังค้นหาอุปกรณ์เพื่อเพิ่ม...\" ให้กดรูปเฟือง (การตั้งค่า) มุมล่างซ้าย (กรอบแดง)"
    },
    {
     "n": 7,
     "caption": "หน้า \"การตั้งค่า\" ข้อ 1. หัวข้อ \"การกำหนดค่าเครือข่าย\" เลือก \"แชร์ Wi-Fi\" (ในรูปต่ออยู่กับ Wi-Fi ชื่อ cloud) — ตอนนี้ \"การกำหนดเซิร์ฟเวอร์ MDM\" ยังเป็น \"ไม่มี\""
    },
    {
     "n": 8,
     "caption": "เลื่อนลงมาที่ \"การกำหนดเซิร์ฟเวอร์ MDM\" เลือก \"ระบุเฉพาะ\" (ไม่ใช่ ไม่มี / ค่าเริ่มต้น) แล้วจะขึ้นเซิร์ฟเวอร์ MDM ด้านล่าง"
    },
    {
     "n": 9,
     "caption": "หน้า \"เลือกเซิร์ฟเวอร์ MDM\" มี 2 อัน ให้ติ๊กเลือก \"MDM\" (ไม่ใช่ ICON FRUIT)"
    },
    {
     "n": 10,
     "caption": "หน้า \"การจัดการอุปกรณ์\" กรอกรหัสผู้ค้า/บัญชี (ช่องบังคับ) ชื่อลูกค้า เบอร์โทรลูกค้า รหัสสัญญา แล้วกด \"ลงทะเบียนทันที\""
    },
    {
     "n": 11,
     "caption": "ตารางราคา iPhone รีไฟแนนซ์ผ่อนรายเดือน (THUNDERCLOUD) แยกตามรุ่น ราคาที่ได้ งวด และจำนวนผ่อน/เดือน — ท้ายตารางระบุ รับเครื่อง TH/ZP เท่านั้น แบตต่ำกว่า 75 ไม่รับ และมีค่าทำสัญญา 400 บาททุกรายการ (update 17/1/2026)"
    },
    {
     "n": 12,
     "caption": "หน้าจอ error ตอนลงชื่อเข้า ขึ้นว่า \"ผู้ใช้ไม่ได้รับอนุญาต\" — บัญชีที่ใช้ไม่มีบทบาทตัวจัดการการลงทะเบียนอุปกรณ์"
    },
    {
     "n": 13,
     "caption": "เอกสาร \"ตัวอย่างรับเคสออนไลน์\" — เงื่อนไขรับเครื่อง (รับ 12 Promax ขึ้นไป, TH/A-ZP/A, แบต 76% ขึ้นไป, รอบชาร์จ) พร้อมตัวอย่างวิธีดูหมายเลขรุ่นและสุขภาพแบตเตอรี่/จำนวนรอบชาร์จ"
    },
    {
     "n": 14,
     "caption": "ตัวอย่างฟอร์มข้อความรับซื้อออนไลน์ — สัญญาเลขที่ TSTR-… รุ่น/ความจุ/สี/แบต/สภาพ เลขประจำเครื่อง ยอด หักค่าบริการ 400 ยอดที่ต้องโอน เบอร์ ไลน์ เลขบัญชี ช่องทางที่รู้จัก+ลิงก์ ที่อยู่ปัจจุบัน ที่อยู่ที่ทำงาน และเบอร์บุคคลอื่นที่ติดต่อได้"
    },
    {
     "n": 15,
     "caption": "เอกสาร \"การส่งเคสลูกค้าออนไลน์\" — รายการที่ต้องถ่าย/พิมพ์ส่ง, ตัวอย่างการแสกนเครื่อง และสรุป 5 ขั้นตอนวิธีเข้าแอพ Configurator"
    },
    {
     "n": 16,
     "caption": "\"ตัวอย่างถ่ายรูปเครื่อง\" 9 รูป — หน้าการตั้งค่า, เกี่ยวกับ (หมายเลขรุ่น/เลขประจำเครื่อง), หน้า IMEI/EID/ICCID, สุขภาพแบตเตอรี่, หน้าจอล็อก, ด้านข้างขวา-ซ้าย, ด้านหลัง, ด้านล่าง"
    },
    {
     "n": 17,
     "caption": "ตัวอย่างถ่ายบัตรประชาชน — บัตรเดี่ยว, ลูกค้าถือบัตรครึ่งตัว, ลูกค้าถือเครื่องเปิดหน้าเกี่ยวกับ, วางบัตรบนเครื่องที่เปิดหน้าการตั้งค่า และสัญญา 2 แผ่นที่เซ็นฝั่งซ้ายแล้ว"
    },
    {
     "n": 18,
     "caption": "หน้าจอ error \"กำลังกำหนดค่า iPhone\" ระหว่างติดตั้งการกำหนดค่าจาก I CON FRUIT AND FOOD LIMITED PARTNERSHIP ขึ้นว่า การติดตั้งโปรไฟล์ไม่สำเร็จ เกิดข้อผิดพลาดเครือข่าย"
    }
   ],
   "steps": [
    {
     "title": "เช็คเครื่องลูกค้าก่อนรับเคส",
     "detail": "รับเฉพาะ 12 Promax ขึ้นไป เช็คหมายเลขรุ่นในหน้าเกี่ยวกับว่าเป็น TH/A หรือ ZP/A เท่านั้น เช็คสุขภาพแบตเตอรี่และจำนวนรอบการชาร์จ และเช็คสภาพเครื่องทุกครั้งก่อนทำสัญญา",
     "page": 13
    },
    {
     "title": "เปิดแอป Configurator",
     "detail": "เปิดแอป Configurator บนเครื่องเอเจนต์ (เครื่องที่ใช้สแกน ไม่ใช่เครื่องลูกค้า)",
     "page": 1
    },
    {
     "title": "กรอกเมลที่ใช้ลงทะเบียน",
     "detail": "ที่หน้า \"ลงชื่อเข้า\" ช่อง \"ที่อยู่อีเมล\" กรอก mmdl@zxcv.marenatech.com แล้วกด \"ดำเนินการต่อ\"",
     "page": 2
    },
    {
     "title": "เลือก \"ใช้บัญชี Apple อื่น\"",
     "detail": "ถ้าเด้งถามว่าจะใช้บัญชี Apple ที่ค้างอยู่ในเครื่องสำหรับ iCloud หรือไม่ ให้กด \"ใช้บัญชี Apple อื่น\" ห้ามกด \"ลงชื่อเข้า\"",
     "page": 3
    },
    {
     "title": "กดลงชื่อเข้า",
     "detail": "หน้า \"ต้องลงชื่อเข้าด้วยบัญชี Apple\" จะขึ้นอีเมล mmdl@zxcv.marenatech.com ให้อยู่แล้ว กดปุ่ม \"ลงชื่อเข้า\" ได้เลย",
     "page": 4
    },
    {
     "title": "ยืนยันบัญชีองค์กร",
     "detail": "หน้า \"บัญชี Apple สำหรับองค์กรของคุณ\" จะพาไปยัง https://mmdl.mdmultra.com เพื่อลงชื่อเข้าบัญชี I CON FRUIT AND FOOD LIMITED PARTNERSHIP กด \"ดำเนินการต่อ\"",
     "page": 5
    },
    {
     "title": "เข้าหน้าการตั้งค่า (รูปเฟือง)",
     "detail": "เมื่อเข้าหน้าสแกน \"กำลังค้นหาอุปกรณ์เพื่อเพิ่ม...\" ให้กดรูปเฟืองมุมล่างซ้ายก่อน เพื่อตั้งค่าให้ครบก่อนสแกน",
     "page": 6
    },
    {
     "title": "ตั้งการกำหนดค่าเครือข่าย = แชร์ Wi-Fi",
     "detail": "ในหัวข้อ \"การกำหนดค่าเครือข่าย\" เลือก \"แชร์ Wi-Fi\" เครือข่าย Wi-Fi ที่เครื่องเอเจนต์ต่ออยู่จะถูกแชร์ให้เครื่องลูกค้า",
     "page": 7
    },
    {
     "title": "ตั้งการกำหนดเซิร์ฟเวอร์ MDM = ระบุเฉพาะ",
     "detail": "เลื่อนลงมาที่ \"การกำหนดเซิร์ฟเวอร์ MDM\" (ค่าตั้งต้นเป็น \"ไม่มี\") ให้เปลี่ยนเป็น \"ระบุเฉพาะ\"",
     "page": 8
    },
    {
     "title": "เลือกเซิร์ฟเวอร์ชื่อ MDM",
     "detail": "ในหน้า \"เลือกเซิร์ฟเวอร์ MDM\" ติ๊กเลือกอันที่ชื่อ \"MDM\" ไม่ใช่ \"ICON FRUIT\" แล้วกดย้อนกลับ จากนั้นกด \"เสร็จสิ้น\" มุมบนซ้ายของหน้าการตั้งค่า",
     "page": 9
    },
    {
     "title": "สแกนเครื่องลูกค้า",
     "detail": "กลับมาหน้าสแกน แล้วสแกนเครื่องลูกค้าเพื่อเพิ่มเข้าระบบ",
     "page": 6
    },
    {
     "title": "กรอกข้อมูลลงทะเบียนเครื่อง",
     "detail": "ที่หน้า \"การจัดการอุปกรณ์\" กรอกรหัสผู้ค้า/บัญชี (ช่องบังคับ) ชื่อลูกค้า เบอร์โทรลูกค้า และรหัสสัญญา แล้วกด \"ลงทะเบียนทันที\"",
     "page": 10
    },
    {
     "title": "ถ่ายรูปเครื่องให้ครบ",
     "detail": "ถ่ายหน้าการตั้งค่า, หน้าเกี่ยวกับ (หมายเลขรุ่น/เลขประจำเครื่อง), หน้า IMEI, สุขภาพแบตเตอรี่, หน้าจอล็อก, ด้านข้างซ้าย-ขวา, ด้านหลัง และด้านล่าง",
     "page": 16
    },
    {
     "title": "ถ่ายบัตรประชาชนและรูปคู่ลูกค้า",
     "detail": "ถ่ายบัตรประชาชน พิมพ์เลขบัตรและที่อยู่ตามบัตร รบกวนลูกค้าถ่ายรูปถือบัตรประชาชน (ครึ่งตัว) ถ่ายรูปคู่กับเครื่องที่จำนำเปิดหน้าเกี่ยวกับ (ครึ่งตัว) และวางบัตรประชาชนบนเครื่องที่เปิดหน้าการตั้งค่า",
     "page": 17
    },
    {
     "title": "เซ็นสัญญาก่อนส่งงาน",
     "detail": "ให้ลูกค้าเซ็นสัญญาฝั่งซ้ายทั้งหมด 2 แผ่น ต้องเซ็นก่อนส่งงานทุกครั้ง",
     "page": 17
    },
    {
     "title": "ส่งข้อมูลตามฟอร์มรับซื้อออนไลน์",
     "detail": "พิมพ์ส่งตามฟอร์ม: สัญญาเลขที่ TSTR-… รุ่น/ความจุ/สี/แบต/สภาพ เลขประจำเครื่อง ยอด หักค่าบริการ 400 ยอดที่ต้องโอน เบอร์ ไลน์ เลขบัญชี+ชื่อ ช่องทางที่ลูกค้ารู้จัก (Google/Tiktok/Facebook) พร้อมลิงก์ ที่อยู่ปัจจุบัน (หรือลิงก์ Google map) ที่อยู่ที่ทำงาน และเบอร์บุคคลอื่นที่ติดต่อได้",
     "page": 14
    }
   ],
   "warnings": [
    "ตอนเด้งถามบัญชี Apple ต้องกด \"ใช้บัญชี Apple อื่น\" เท่านั้น ถ้าเผลอกด \"ลงชื่อเข้า\" จะไปใช้บัญชี iCloud ส่วนตัวที่ค้างอยู่ในเครื่อง (รูป 3)",
    "การกำหนดเซิร์ฟเวอร์ MDM ค่าตั้งต้นเป็น \"ไม่มี\" ต้องเปลี่ยนเป็น \"ระบุเฉพาะ\" ไม่ใช่ \"ค่าเริ่มต้น\" (รูป 7, 8)",
    "หน้าเลือกเซิร์ฟเวอร์ MDM มี 2 อัน ต้องเลือกอันชื่อ \"MDM\" ไม่ใช่ \"ICON FRUIT\" (รูป 9)",
    "ถ้าขึ้น \"ผู้ใช้ไม่ได้รับอนุญาต\" แปลว่าบัญชีที่ลงชื่อเข้าไม่มีบทบาทตัวจัดการการลงทะเบียนอุปกรณ์ ให้เช็คว่าใช้อีเมล mmdl@zxcv.marenatech.com ถูกตัวหรือยัง (รูป 12)",
    "ถ้าขึ้น \"การติดตั้งโปรไฟล์ไม่สำเร็จ เกิดข้อผิดพลาดเครือข่าย\" ให้เช็คเน็ต/Wi-Fi ก่อน แล้วทำใหม่ (รูป 18)",
    "ร้านรับเฉพาะ 12 Promax ขึ้นไป และรับเฉพาะเครื่อง TH/A กับ ZP/A เท่านั้น เช็คจากหมายเลขรุ่นในหน้าเกี่ยวกับ (รูป 13)",
    "เงื่อนไขแบตเตอรี่ 2 เอกสารเขียนไม่ตรงกัน: รูป 13 เขียนว่ารับ 76% ขึ้นไป และต่ำกว่า 80% หัก 500 บาท ส่วนตารางราคา (รูป 11) เขียนว่าราคานี้คือแบต 80%-100% แบต 75%-79% ลด 500 บาท และแบตต่ำกว่า 75% ไม่รับ — ถ้าเคสก้ำกึ่งให้เช็คกับร้านก่อน",
    "ต้องเช็ครอบการชาร์จของลูกค้าด้วย เอกสารระบุ \"รับรอบการชาร์จ 5-10 รอบขึ้นไป\" (รูป 13)",
    "ตารางราคาระบุว่ามีค่าทำสัญญาและติดตั้งระบบความปลอดภัย 400 บาททุกรายการ และให้หักจากยอดที่ลูกค้าได้รับ (รูป 11, 14)",
    "เลขบัญชีที่โอนต้องตรงกับชื่อผู้ทำสัญญาและบัตรประชาชน (รูป 14)",
    "สัญญาของลูกค้าต้องเซ็นฝั่งซ้ายทั้งหมด 2 แผ่น และต้องเซ็นก่อนส่งงานทุกครั้ง (รูป 17)",
    "รูปลูกค้าถือบัตรประชาชนและรูปลูกค้าถือเครื่อง ให้ถ่ายแค่ครึ่งตัว (รูป 15)"
   ]
  },
  {
   "slug": "bypass-plus",
   "title": "คู่มือ iOSTools — ขึ้นล็อก iPhone แบบไม่ต้องล้างเครื่อง",
   "subtitle": "ใช้เมื่อลูกค้าไม่อยากล้างเครื่อง แต่เราต้องขึ้นล็อก — รูป แอป ข้อมูล ค่าตั้งค่า อยู่ครบ",
   "icon": "🔐",
   "summary": "คู่มือใช้โปรแกรม iOSTools (เว็บระบบ iostools.cc) ขึ้นล็อกเครื่อง iPhone โดยไม่ต้องล้างเครื่อง ข้อมูลลูกค้า รูป แอป และค่าตั้งค่าอยู่ครบเหมือนเดิม มี 6 ขั้นตอน ตั้งแต่อนุญาต Serial Number ในระบบ ต่อสายกด Trust เปิด Supervision (ADE) จับคู่เข้า ABM ด้วย Apple Configurator รีสตาร์ทเครื่อง จนถึงกด Enroll This iPhone ใช้ขั้นตอนเดียวกันทั้งแอดมินและแมสหน้างาน ถ้าลูกค้ายอมให้ล้างเครื่องอยู่แล้วไม่ต้องใช้คู่มือนี้",
   "keywords": [
    "ขึ้นล็อกไม่ล้างเครื่อง",
    "iOSTools",
    "iostools.cc",
    "bypass",
    "แลกเงิน Plus",
    "Supervision",
    "ADE",
    "ABM",
    "Apple Configurator",
    "Serial Number",
    "Trust This Computer",
    "Find My iPhone",
    "Enroll This iPhone",
    "Restart and Re-enroll",
    "License Key"
   ],
   "pages": [
    {
     "n": 1,
     "caption": "หน้าปก \"คู่มือ iOSTools\" (ป้ายบนสุด: iOSTools · ฟังก์ชันเสริม) — ขึ้นล็อกเครื่อง iPhone แบบ \"ไม่ต้องล้างเครื่อง\" ข้อมูลลูกค้าอยู่ครบ (รูป/แอป/ค่าตั้งค่า) ด้านล่างมีกล่อง \"ใช้ตอนไหน?\" เทียบสองช่อง: ✅ ใช้ iOSTools เมื่อลูกค้าไม่อยากล้างเครื่อง กับ ✕ ไม่ต้องใช้เมื่อลูกค้ายอมให้ล้างเครื่อง (ขึ้นล็อกตามขั้นตอนปกติของบริษัทได้เลย) ท้ายหน้าระบุเว็บระบบ iostools.cc ใช้ขั้นตอนเดียวกันทั้งแอดมินและแมสหน้างาน"
    },
    {
     "n": 2,
     "caption": "แถบหัวข้อ \"ขั้นตอนการใช้งาน (6 ขั้น)\" + กล่องแดง \"2 ข้อสำคัญที่ห้ามลืม\" (① ปิด Find My iPhone ก่อนเสมอ ② หลังจับคู่สำเร็จ ห้ามถอดสาย จนกว่าจะรีสตาร์ทเสร็จ) ตามด้วยขั้นที่ 1 อนุญาตเครื่องในระบบ (Authorize Device) — รูปหน้า Add Serial Number (มีช่อง Allowed Modes และกล่อง Batch Add ใส่ทีละบรรทัด) และหน้า Licenses พร้อมป๊อปอัป Generate License Key ที่ตั้ง License Quota (Credits)"
    },
    {
     "n": 3,
     "caption": "ขั้นที่ 2 ต่อสาย + กด Trust (Trust This Computer) — ต่อ iPhone เข้าคอมด้วยสาย Data แล้วกด Trust บนเครื่องลูกค้า โปรแกรม iOS Tools จะขึ้น Device Connected และโชว์ข้อมูลเครื่อง (รุ่น, iOS, Serial Number, DEP/MDM Status) กล่อง Important Tips ย้ำให้ปิด Find My iPhone ก่อน (Settings > [Your Name] > Find My > Find My iPhone > Off)"
    },
    {
     "n": 4,
     "caption": "ขั้นที่ 3 เปิด Supervision — กดปุ่ม \"Enable Supervision (ADE)\" ในโปรแกรม แล้วรอเครื่องเด้งไปหน้า Choose a Wi-Fi Network สถานะมุมขวาบนขึ้น Device Ready กล่อง Tip บอกว่าถ้าเครื่องไม่เด้งไปหน้า Wi-Fi ให้ข้าม (skip) Wi-Fi แล้วย้อนกลับมาหน้า Wi-Fi ใหม่"
    },
    {
     "n": 5,
     "caption": "ขั้นที่ 4 จับคู่เข้า ABM (Add to Apple Business Manager) — หน้าจอ iPhone ขึ้น \"Add this iPhone to your organization\" พร้อมภาพโค้ดลายจุด ให้ใช้อีกเครื่องที่เปิด Apple Configurator สแกน วางภาพให้อยู่ในวงกลม (Place the image in the circle) มีปุ่ม Manual Pairing สำรอง กล่อง Important ย้ำว่า Apple Configurator ต้องล็อกอินบัญชีที่มีสิทธิ์จัดการเครื่องใน ABM เมื่อจับคู่สำเร็จเครื่องจะถูกเพิ่มเข้า Apple Business Manager อัตโนมัติ"
    },
    {
     "n": 6,
     "caption": "ขั้นที่ 5 รีสตาร์ทเครื่อง (Restart and Re-enroll) — อย่าถอดสาย! กดปุ่ม \"Restart and Re-enroll Device\" ในโปรแกรม เครื่องจะรีสตาร์ทเองแล้วเข้าขั้นตอนขึ้นระบบ Supervision ต่อ หน้าจอ iPhone โชว์ \"iPhone Added — This iPhone has been added to ... LIMITED / now managed by Apple Business Services via iOS Tools\""
    },
    {
     "n": 7,
     "caption": "ขั้นที่ 6 กดยืนยัน — เสร็จ (Activate the Device and Complete Enrollment) — ระหว่าง activation ปกติของเครื่อง จะมีหน้า Device Management บอกว่า This iPhone is owned by: LIMITED ให้กดปุ่มน้ำเงิน \"Enroll This iPhone\" (ใต้ปุ่มมี \"Remove iPhone from Organization\" — ห้ามกดเด็ดขาด) แล้วขึ้นล็อกสำเร็จ"
    }
   ],
   "steps": [
    {
     "title": "อนุญาตเครื่องในระบบ (Authorize Device)",
     "detail": "เข้าเว็บ iostools.cc ล็อกอินเข้า admin panel มี 2 วิธี: (1) อนุญาตตาม Serial Number — ไปหน้า Serial Numbers ใส่ Serial Number ของเครื่อง ติ๊ก Allowed Modes เป็น Supervised Mode (ADE) แล้วกด Submit ถ้าลงหลายเครื่องพร้อมกันใช้กล่อง Batch Add ใส่ทีละบรรทัดแล้วกด Batch Add (2) อนุญาตด้วย License Key — ไปหน้า Licenses ตั้ง License Quota (Credits) เลือก Allowed Modes แล้วกด Generate License Key วิธีนี้ให้โควตาเป็นจำนวน Credits โดยไม่ผูกกับเครื่องใดเครื่องหนึ่ง",
     "page": 2
    },
    {
     "title": "ต่อสาย + กด Trust (Trust This Computer)",
     "detail": "ปิด Find My iPhone ก่อน (ตั้งค่า → [ชื่อ] → Find My → Find My iPhone → ปิด) จากนั้นต่อ iPhone เข้าคอมด้วยสาย Data แล้วกด \"Trust\" บนเครื่องลูกค้า เพื่อให้ iostools เข้าถึงและจัดการข้อมูลเครื่องได้ โปรแกรมจะขึ้นสถานะ Device Connected และโชว์ข้อมูลเครื่อง (รุ่น, เวอร์ชัน iOS, Serial Number, DEP Status, MDM Status)",
     "page": 3
    },
    {
     "title": "เปิด Supervision (ADE)",
     "detail": "ในโปรแกรมกดปุ่ม \"Enable Supervision (ADE)\" แล้วรอเครื่องเด้งไปหน้า Choose a Wi-Fi Network สถานะมุมขวาบนจะขึ้น Device Ready ถ้าเครื่องไม่เด้งไปหน้า Wi-Fi ตามปกติ ให้ข้าม (skip) Wi-Fi แล้วย้อนกลับมาหน้า Wi-Fi ใหม่",
     "page": 4
    },
    {
     "title": "จับคู่เข้า ABM (Add to Apple Business Manager)",
     "detail": "ใช้อีกเครื่อง (iPhone/iPad อีกตัว) เปิดแอป Apple Configurator ที่ล็อกอินด้วยบัญชี Apple Business Manager ซึ่งมีสิทธิ์จัดการเครื่อง แล้วเลือก MDM server ปลายทางที่จะจับคู่ เมื่อหน้าจอ iPhone ลูกค้าขึ้น \"Add this iPhone to your organization\" พร้อมภาพโค้ดลายจุด ให้ใช้ Apple Configurator สแกน วางภาพให้อยู่ในวงกลม (ถ้าสแกนไม่ติดใช้ Manual Pairing) เมื่อจับคู่สำเร็จเครื่องจะถูกเพิ่มเข้า Apple Business Manager อัตโนมัติ",
     "page": 5
    },
    {
     "title": "รีสตาร์ทเครื่อง (Restart and Re-enroll)",
     "detail": "หลังจับคู่ใน Apple Configurator สำเร็จ ห้ามถอดสาย! กดปุ่ม \"Restart and Re-enroll Device\" ในโปรแกรม (บางบิลด์ปุ่มนี้ชื่อ \"Restart and Register Device\" — ปุ่มเดียวกัน) เครื่องจะรีสตาร์ทเองแล้วเข้าขั้นตอนขึ้นระบบ Supervision ต่อ หน้าจอ iPhone จะขึ้น \"iPhone Added\" บอกว่าเครื่องถูกเพิ่มเข้าองค์กรและถูกจัดการโดย Apple Business Services ผ่าน iOS Tools แล้ว",
     "page": 6
    },
    {
     "title": "กดยืนยัน — เสร็จ (Enroll This iPhone)",
     "detail": "เครื่องเปิดมาระหว่างขั้นตอน activation ปกติ จะมีหน้า Device Management บอกว่าเครื่องนี้เป็นของบริษัท (This iPhone is owned by: LIMITED) และองค์กรจะจัดการอีเมล บัญชีเครือข่าย แอป และค่าตั้งค่าของเครื่อง ให้กดปุ่มน้ำเงิน \"Enroll This iPhone\" เครื่องจะเข้า MDM = ขึ้นล็อกสำเร็จ โดยข้อมูลลูกค้ายังอยู่ครบ",
     "page": 7
    }
   ],
   "warnings": [
    "ปิด Find My iPhone ก่อนเริ่มเสมอ (ตั้งค่า > [ชื่อ] > Find My > Find My iPhone > ปิด) ถ้าไม่ปิดจะมีปัญหาตอนเชื่อมต่อหรือตอนขึ้นระบบ",
    "หลังจับคู่ใน Apple Configurator สำเร็จแล้ว ห้ามถอดสาย จนกว่าจะกด Restart and Re-enroll Device และเครื่องรีสตาร์ทเสร็จ",
    "หน้า Device Management ต้องกด \"Enroll This iPhone\" เท่านั้น ห้ามกด \"Remove iPhone from Organization\" ที่อยู่ใต้ปุ่ม เพราะจะเป็นการถอดเครื่องออกจากองค์กร",
    "ปุ่มรีสตาร์ทในโปรแกรมชื่อไม่ตรงกันแล้วแต่บิลด์ — บางเครื่องขึ้น \"Restart and Register Device\" บางเครื่องขึ้น \"Restart and Re-enroll Device\" เป็นปุ่มเดียวกัน อย่าสับสน",
    "Apple Configurator ต้องล็อกอินด้วยบัญชีที่มีสิทธิ์จัดการเครื่องใน ABM และต้องเลือก MDM server ปลายทางให้ถูก ไม่งั้นเครื่องจะไม่เข้า Apple Business Manager",
    "ถ้าเครื่องไม่เด้งไปหน้า Wi-Fi หลังกด Enable Supervision (ADE) ให้กดข้าม (skip) Wi-Fi แล้วย้อนกลับมาหน้า Wi-Fi ใหม่",
    "Serial Number ต้องไม่เกิน 16 ตัวอักษร และห้ามเป็นตัวเลขล้วน (ใช้ได้ทั้งช่อง Add Serial Number และ Batch Add)",
    "License Quota = 0 คือไม่มีโควตาล่วงหน้า การจ่ายทีหลัง (paid auth) จะล้มเหลวถ้าโควตาไม่พอ",
    "ถ้าลูกค้ายอมให้ล้างเครื่อง ไม่ต้องใช้ iOSTools — ขึ้นล็อกตามขั้นตอนปกติของบริษัทได้เลย"
   ]
  },
  {
   "slug": "line-payment",
   "title": "ชำระเงินผ่านไลน์",
   "subtitle": "ใช้ตอนลูกค้าถามว่าจ่ายค่างวด/ค่าบริการ/ปิดสัญญา ผ่าน LINE ยังไง",
   "icon": "💬",
   "summary": "คู่มือสอนลูกค้าจ่ายเงินผ่านแชท LINE OA @thundercloud แค่ 3 ขั้นตอน คือ เชื่อมบัญชีด้วยเลขบัตรประชาชน กดปุ่ม \"เมนู\" ด้านล่างแชท แล้วเลือกวิธีชำระ ระบบจะส่ง QR Code มาให้สแกนจ่ายผ่านแอปธนาคาร วิธีชำระมีให้เลือก 3 แบบ คือ เช็คชำระค่างวด ชำระค่าบริการ และซื้อคืน (ปิดสัญญา) พนักงานหน้าร้านใช้อธิบายลูกค้าที่โทรมาถามวิธีจ่ายเงิน",
   "keywords": [
    "ชำระเงินผ่านไลน์",
    "จ่ายผ่าน LINE",
    "LINE OA thundercloud",
    "เชื่อมบัญชี",
    "เลขบัตรประชาชน 13 หลัก",
    "สแกน QR",
    "QR Code หมดอายุ 30 นาที",
    "เช็คชำระค่างวด",
    "check and pay",
    "ชำระค่าบริการ",
    "service fee",
    "ซื้อคืน ปิดสัญญา",
    "buy back",
    "ค่าดำเนินการล่าช้า เลยกำหนด",
    "เมนูไลน์ list menu"
   ],
   "pages": [
    {
     "n": 1,
     "caption": "หน้าปกคู่มือ \"วิธีชำระเงินผ่าน LINE\" (THUNDER CLOUD · PAYMENT GUIDE) — จ่ายค่างวด · ค่าบริการ · ปิดสัญญา ผ่านแชท LINE ง่ายๆ แค่ 3 ขั้นตอน มีเบอร์ 082-123-2551, LINE : @thundercloud และป้าย \"ปลอดภัย · รวดเร็ว · ทันใจ\" ถัดมาเป็นการ์ดสรุป 3 ขั้นตอน คือ 1 เชื่อมบัญชี (พิมพ์เลขบัตร ปชช.) 2 เลือกเมนู (จาก List Menu) 3 สแกน QR ชำระ (ผ่านแอปธนาคาร) ด้านล่างเป็นขั้นตอนที่ 1 เชื่อมบัญชี ให้พิมพ์ในแชทว่า \"เชื่อม\" เว้นวรรค แล้วตามด้วยเลขบัตรประชาชน 13 หลัก ตัวอย่าง \"เชื่อม 2222222222222\" พร้อมกล่องเตือนว่าทำครั้งเดียว ครั้งต่อไปกดเมนูได้เลย ไม่ต้องเชื่อมใหม่"
    },
    {
     "n": 2,
     "caption": "ขั้นตอนที่ 2 เลือกเมนู — กดปุ่ม \"เมนู ▲\" ด้านล่างแชท จะเจอเมนูบริการ (List Menu) แล้วเลือกรายการที่ต้องการ ภาพหน้าจอแสดงเมนู 5 ช่อง คือ เช็คชำระค่างวด (ตรวจสอบยอด/สถานะ), ชำระค่าบริการ, ซื้อคืน, เชื่อมต่อข้อมูล และรูปออนไลน์ แต่ละช่องมีปุ่ม \"กดเลย →\" ตรงกลางเป็นการ์ดแบรนด์ THUNDERCLOUD พร้อมเบอร์ 082-123-2551 และ @thundercloud"
    },
    {
     "n": 3,
     "caption": "ขั้นตอนที่ 3 เลือกวิธีชำระ แล้วสแกน QR — มีให้เลือก 3 แบบ กดเมนูที่ต้องการ ระบบจะส่ง QR Code มาให้ นำไปสแกนจ่ายผ่านแอปธนาคารได้เลย ตัวอย่างแรกคือเมนู \"เช็คชำระค่างวด\" (CHECK & PAY) ระบบส่งการ์ดสัญญามาในแชท แสดงเลขที่สัญญา (เบลอ), รายการเช่า iPhone — I phone 15 ZP/A 128GB สีเขียว แบต 97% สภาพ 90%, รอบชำระทุก 10 วัน, วันที่เริ่มเช่า 31/05/2026, ชำระครั้งถัดไป 30/06/2026, ค่าเช่า ฿600.00, ค่าดำเนินการล่าช้า ฿400.00, ยอดชำระ ฿1,000.00 ด้านบนการ์ดขึ้นแถบแดง \"🔴 เลยกำหนด | เกิน 5 วัน\" ใต้ภาพเป็นการ์ดอธิบายเมนู \"เช็คยอดที่ต้องจ่ายในงวดนี้ แล้วจ่ายค่างวด\" พร้อมปุ่ม \"→ ดูยอด + รับ QR จ่ายค่างวด\""
    },
    {
     "n": 4,
     "caption": "วิธีชำระแบบที่ 2 เมนู \"ชำระค่าบริการ\" (SERVICE FEE) — ภาพหน้าจอแชทแสดง QR Code ที่ระบบส่งมา พร้อมข้อความ \"QR ชำระเงินสัญญา [เลขที่เบลอ] ยอด ฿1,000.00 / สแกน QR นี้ด้วยแอปธนาคารเพื่อชำระเงิน / ⏱ กรุณาชำระภายใน 30 นาที\" ใต้ภาพเป็นการ์ดอธิบายเมนู \"จ่ายยอดค่าบริการ ง่าย ปลอดภัย\" พร้อมปุ่ม \"→ รับ QR จ่ายค่าบริการ\""
    },
    {
     "n": 5,
     "caption": "วิธีชำระแบบที่ 3 เมนู \"ซื้อคืน (ปิดสัญญา)\" (BUY BACK) — ภาพหน้าจอแชทแสดง QR พร้อมข้อความ \"QR ปิดสัญญา (ซื้อคืน) [เลขที่เบลอ] ยอด ฿[เบลอ] / สแกน QR นี้ด้วยแอปธนาคารเพื่อปิดสัญญา / ⏱ กรุณาชำระภายใน 30 นาที\" ใต้ภาพเป็นการ์ดอธิบายเมนู \"จ่ายปิดยอดทั้งหมดเพื่อปิดสัญญา\" พร้อมปุ่ม \"→ รับ QR ปิดสัญญา\" ปิดท้ายด้วยการ์ดสีน้ำเงิน \"สแกน QR ด้วยแอปธนาคารเพื่อชำระเงิน — หาก QR หมดอายุ ให้กดเมนูขอ QR ใหม่อีกครั้งได้ทันที\" และตัวเลขใหญ่ \"30 นาที · ต่อ 1 QR\""
    },
    {
     "n": 6,
     "caption": "ท้ายคู่มือ แถบข้อมูลติดต่อ \"Thunder Cloud — บริการดี รวดเร็ว ทันใจ · 📞 082-123-2551 · 💬 LINE @thundercloud\""
    }
   ],
   "steps": [
    {
     "title": "ขั้นตอนที่ 1 เชื่อมบัญชีด้วยเลขบัตรประชาชน",
     "detail": "ให้ลูกค้าพิมพ์ในแชท LINE ว่า \"เชื่อม\" เว้นวรรค แล้วตามด้วยเลขบัตรประชาชน 13 หลัก เช่น เชื่อม 2222222222222 — ทำแค่ครั้งเดียว ครั้งต่อไปกดเมนูได้เลย ไม่ต้องเชื่อมใหม่",
     "page": 1
    },
    {
     "title": "ขั้นตอนที่ 2 กดปุ่ม \"เมนู\" ด้านล่างแชท",
     "detail": "กดปุ่ม \"เมนู ▲\" ที่อยู่ด้านล่างช่องแชท จะเจอเมนูบริการ (List Menu) ของ THUNDERCLOUD มีให้เลือก เช็คชำระค่างวด, ชำระค่าบริการ, ซื้อคืน, เชื่อมต่อข้อมูล และรูปออนไลน์ แต่ละช่องกดที่ปุ่ม \"กดเลย →\"",
     "page": 2
    },
    {
     "title": "ขั้นตอนที่ 3 เลือกวิธีชำระ (มีให้เลือก 3 แบบ) แล้วสแกน QR",
     "detail": "กดเมนูวิธีชำระที่ต้องการ ระบบจะส่ง QR Code มาให้ในแชท นำไปสแกนจ่ายผ่านแอปธนาคารได้เลย ทั้ง 3 แบบเป็นทางเลือก ไม่ต้องทำเรียงกัน เลือกตามที่ลูกค้าจะจ่าย",
     "page": 3
    },
    {
     "title": "ตัวเลือกที่ 1 — เช็คชำระค่างวด (CHECK & PAY)",
     "detail": "ใช้เมื่อลูกค้าจะเช็คยอดที่ต้องจ่ายในงวดนี้ แล้วจ่ายค่างวด ระบบส่งการ์ดสัญญามาให้ บอกเลขที่สัญญา รายการเช่า รอบชำระ วันที่เริ่มเช่า วันชำระครั้งถัดไป ค่าเช่า ค่าดำเนินการล่าช้า และยอดชำระรวม กดปุ่ม \"ดูยอด + รับ QR จ่ายค่างวด\" เพื่อรับ QR",
     "page": 3
    },
    {
     "title": "ตัวเลือกที่ 2 — ชำระค่าบริการ (SERVICE FEE)",
     "detail": "ใช้เมื่อลูกค้าจะจ่ายยอดค่าบริการ กดปุ่ม \"รับ QR จ่ายค่าบริการ\" ระบบจะส่ง QR พร้อมยอดมาให้ในแชท",
     "page": 4
    },
    {
     "title": "ตัวเลือกที่ 3 — ซื้อคืน (ปิดสัญญา) (BUY BACK)",
     "detail": "ใช้เมื่อลูกค้าจะจ่ายปิดยอดทั้งหมดเพื่อปิดสัญญา กดปุ่ม \"รับ QR ปิดสัญญา\" ระบบจะส่ง QR ปิดสัญญามาให้ในแชท",
     "page": 5
    },
    {
     "title": "สแกน QR ด้วยแอปธนาคารเพื่อชำระเงิน",
     "detail": "นำ QR ที่ระบบส่งมาสแกนจ่ายผ่านแอปธนาคาร โดยต้องชำระภายใน 30 นาที หาก QR หมดอายุ ให้กดเมนูขอ QR ใหม่อีกครั้งได้ทันที",
     "page": 5
    }
   ],
   "warnings": [
    "QR มีอายุ 30 นาที ต่อ 1 ใบ หาก QR หมดอายุ ให้กดเมนูขอ QR ใหม่อีกครั้งได้ทันที",
    "การเชื่อมบัญชีต้องพิมพ์ตามรูปแบบนี้เท่านั้น คือ คำว่า \"เชื่อม\" เว้นวรรค แล้วตามด้วยเลขบัตรประชาชน 13 หลัก",
    "เชื่อมบัญชีทำครั้งเดียวพอ ครั้งต่อไปกดเมนูได้เลย ไม่ต้องพิมพ์เชื่อมซ้ำ",
    "ถ้าจ่ายเลยกำหนด การ์ดสัญญาจะขึ้นแถบสีแดง \"เลยกำหนด\" พร้อมจำนวนวันที่เกิน และมีค่าดำเนินการล่าช้าบวกเพิ่มในยอดชำระ (ตัวอย่างในรูป ค่าเช่า 600 + ค่าดำเนินการล่าช้า 400 = ยอดชำระ 1,000 บาท)",
    "ต้องกดปุ่ม \"เมนู ▲\" ด้านล่างช่องแชทก่อน ถึงจะเห็นเมนูบริการ (List Menu)"
   ]
  },
  {
   "slug": "line-backup",
   "title": "วิธีสำรองข้อมูลแชท LINE",
   "subtitle": "ใช้ตอนจะเปลี่ยนเครื่องใหม่ หรือต้องการเก็บแชท LINE ขึ้นคลาวด์กันข้อมูลหาย",
   "icon": "💬",
   "summary": "คู่มือมาตรฐาน 6 ขั้นตอน สำหรับสำรองแชท LINE ขึ้นคลาวด์ก่อนเปลี่ยนเครื่อง ใช้กับ LINE บน iPhone (iOS) ไล่ตั้งแต่กดฟันเฟือง เข้าเมนูสำรองข้อมูลการแชท กำหนดรหัสเรียกคืนข้อมูล 6 หลัก รอสำรองจนเสร็จ ไปจนถึงวิธีเช็กว่าสำรองสำเร็จหรือยัง มีเช็กลิสต์ก่อนเริ่มและข้อควรระวังประกอบ (เอกสาร SOP-LINE-BACKUP-002 เวอร์ชัน 2.0)",
   "keywords": [
    "สำรองแชท",
    "สำรองข้อมูล LINE",
    "สำรองข้อมูลการแชท",
    "backup line",
    "line backup",
    "restore line",
    "ย้ายเครื่อง",
    "เปลี่ยนเครื่อง",
    "รหัสเรียกคืนข้อมูล",
    "รหัส 6 หลัก",
    "กำหนดรหัสเรียกคืนข้อมูล",
    "โอนย้ายบัญชี",
    "แชทหาย",
    "กู้แชท",
    "iCloud"
   ],
   "pages": [
    {
     "n": 1,
     "caption": "หน้า 1 — หัวเรื่อง SOP วิธีสำรองข้อมูลแชท LINE (SOP-LINE-BACKUP-002 v2.0 ใช้กับ LINE บน iPhone) มีเช็กลิสต์ก่อนเริ่ม 4 ข้อ (Wi-Fi เสถียร, แบตเกิน 50%, ล็อกอิน iCloud, อัปเดต LINE), ขั้นตอนที่ 1-3 พร้อมรูปหน้าจอ (กดฟันเฟืองมุมขวาบน → กดสำรองข้อมูลการแชท → กดปุ่มเขียวสำรองข้อมูลทันที) และกล่อง 'ทำไมต้องสำรองข้อมูล' 6 เหตุผล"
    },
    {
     "n": 2,
     "caption": "หน้า 2 — ขั้นตอนที่ 4-6 พร้อมรูปหน้าจอ (กำหนดรหัสเรียกคืนข้อมูล 6 หลัก → หน้ากำลังสำรองข้อมูลขึ้นแถบความคืบหน้า → เด้งถามโอนย้ายบัญชี ให้กด 'ปิด'), กล่อง 'ตรวจผลลัพธ์ — สำรองสำเร็จหรือยัง?' (สำรองครั้งล่าสุด วันนี้ 19:46, ขนาดไฟล์ 47.3 MB, รหัสเรียกคืนขึ้น 'กำหนดแล้ว') และกล่องข้อควรระวัง 4 ข้อ"
    }
   ],
   "steps": [
    {
     "title": "กดฟันเฟือง",
     "detail": "เปิดแอป LINE แล้วแตะไอคอนฟันเฟือง (ตั้งค่า) มุมขวาบนของหน้าหลัก",
     "page": 1
    },
    {
     "title": "กดสำรองข้อมูลการแชท",
     "detail": "ในหน้าตั้งค่า เลื่อนหาหัวข้อ 'สำรองข้อมูล & โอนย้ายบัญชี' แล้วแตะ 'สำรองข้อมูลการแชท'",
     "page": 1
    },
    {
     "title": "กดสำรองข้อมูลทันที",
     "detail": "แตะปุ่มสีเขียว 'สำรองข้อมูลทันที' ด้านล่างจอ",
     "page": 1
    },
    {
     "title": "ใส่รหัสตัวเลข 6 หลัก",
     "detail": "ตั้งรหัสเรียกคืนข้อมูลเป็นตัวเลข 6 หลัก แล้วใส่ซ้ำอีกครั้งเพื่อยืนยัน ห้ามลืมรหัสนี้เด็ดขาด เพราะเป็นรหัสที่ใช้เรียกคืนประวัติการแชทที่สำรองไว้",
     "page": 2
    },
    {
     "title": "รอสำรองข้อมูลจนเสร็จ",
     "detail": "ระยะเวลาขึ้นอยู่กับขนาดข้อมูล ห้ามปิดแอปหรือล็อกจอระหว่างนี้ รอจนแถบความคืบหน้าวิ่งครบ",
     "page": 2
    },
    {
     "title": "เสร็จแล้วกด 'ปิด'",
     "detail": "ถ้าเด้งถามว่า 'ต้องการโอนย้ายบัญชีหรือไม่' ให้กด 'ปิด' — ยังไม่ต้องกดโอนย้ายบัญชี",
     "page": 2
    }
   ],
   "warnings": [
    "รหัส 6 หลักคือกุญแจเดียวในการกู้แชทกลับ — ถ้าลืม ข้อมูลที่สำรองไว้จะกู้คืนไม่ได้เลย ให้จดเก็บไว้ที่ปลอดภัย",
    "ห้ามกด 'ลบข้อมูลที่สำรองไว้' เพราะจะลบทั้งไฟล์สำรองและรหัสเรียกคืนทั้งหมด",
    "ถ้าเวลาสำรองล่าสุดไม่อัปเดต ให้เช็กพื้นที่ iCloud และสัญญาณ Wi-Fi แล้วทำใหม่ตั้งแต่ขั้นตอนที่ 3",
    "ตั้ง 'ความถี่ในการสำรองข้อมูล' เป็นทุกสัปดาห์ เพื่อให้ระบบสำรองอัตโนมัติตอนชาร์จเครื่อง",
    "ก่อนเริ่มต้องต่อ Wi-Fi ที่เสถียร ไม่ควรใช้เน็ตมือถือ เพราะไฟล์สำรองมีขนาดใหญ่",
    "แบตเตอรี่ต้องเหลือเกิน 50% หรือเสียบชาร์จไว้ระหว่างสำรอง",
    "ต้องล็อกอิน iCloud (Apple ID) อยู่ และมีพื้นที่ว่างพอ",
    "ควรอัปเดต LINE เป็นเวอร์ชันล่าสุดก่อนเริ่มทำ",
    "ตรวจผลลัพธ์ทุกครั้งที่หน้า 'สำรองข้อมูลการแชท': วันเวลาสำรองครั้งล่าสุดต้องเป็นปัจจุบัน, ขนาดไฟล์ต้องมีตัวเลข (ไม่ใช่ 0 หรือว่าง), รหัสเรียกคืนข้อมูลต้องขึ้นสถานะ 'กำหนดแล้ว'"
   ]
  },
  {
   "slug": "mass-contract",
   "title": "แมสเซ็นสัญญา + บัตร ปชช",
   "subtitle": "ตัวอย่างรูปที่ต้องถ่ายเก็บตอนลูกค้าเซ็นสัญญาเช่าซื้อ และชุดถ่ายบัตรประชาชนคู่กับเครื่อง",
   "icon": "📝",
   "summary": "คู่มือตัวอย่างรูปที่พนักงานต้องถ่ายเก็บไว้ตอนลูกค้าเซ็นสัญญาเช่าซื้อโทรศัพท์มือถือกับ บริษัท ธันเดอร์คลาวด์ จำกัด แบ่งเป็น 2 ชุด คือ ชุดเซ็นสัญญา 3 ใบ (บัตรประชาชน + ลูกค้าถือสัญญาที่เซ็นแล้วคู่กับเครื่อง + หลังเครื่อง) และชุด \"บัตร ปชช\" 4 ใบ (บัตรเต็มใบ + ลูกค้าถือเครื่องโชว์หน้าจอ \"เกี่ยวกับ\" + บัตรทาบหน้าจอ + ลูกค้าถือบัตรคู่กับหน้า) ตัวอย่างในคู่มือมาจากลูกค้าคนละราย ให้ดูเป็นแบบการจัดรูปเท่านั้น เวลาใช้งานจริงรูปทุกใบต้องเป็นลูกค้าคนเดียวกันและเครื่องเดียวกัน",
   "keywords": [
    "แมสเซ็นสัญญา",
    "เซ็นสัญญา",
    "สัญญาเช่าซื้อ",
    "บัตรประชาชน",
    "บัตร ปชช",
    "ถ่ายบัตรประชาชน",
    "ถ่ายรูปคู่ลูกค้า",
    "หน้าจอเกี่ยวกับ",
    "เลขประจำเครื่อง",
    "หลังเครื่อง",
    "ธันเดอร์คลาวด์",
    "Thunder Cloud",
    "serial number",
    "ID card",
    "contract"
   ],
   "pages": [
    {
     "n": 1,
     "caption": "บัตรประชาชนลูกค้าวางบนคีย์บอร์ดโน้ตบุ๊ก ถ่ายจากด้านบนเต็มใบ เห็นเลขบัตร ชื่อ-นามสกุล ที่อยู่ รูปหน้า วันออกบัตร และวันหมดอายุ (ในรูปมีแสงฮอโลแกรมพาดแถวบนนิดหน่อย แต่ยังอ่านออก)"
    },
    {
     "n": 2,
     "caption": "ลูกค้านั่งที่ออฟฟิศ บริษัท ธันเดอร์คลาวด์ จำกัด (เห็นชื่อบริษัทที่กระจกด้านหลัง) มือหนึ่งถือสัญญาเช่าซื้อโทรศัพท์มือถือที่เซ็นชื่อท้ายสัญญาแล้ว อีกมือถือเครื่องเปิดหน้าจอ \"เกี่ยวกับ\" ถ่ายติดหน้าลูกค้าในรูปเดียวกัน"
    },
    {
     "n": 3,
     "caption": "ด้านหลังเครื่อง iPhone สีไทเทเนียม ถอดเคสออก ถือขึ้นมาถ่ายให้เห็นทั้งเครื่องและกล้องหลังชัด"
    },
    {
     "n": 4,
     "caption": "บัตรประชาชน (ลูกค้าอีกราย) ถ่ายใบเดี่ยวเต็มใบบนพื้นเรียบ อ่านเลขบัตร ชื่อ-นามสกุล ที่อยู่ วันออกบัตร-วันหมดอายุ ได้ครบ ไม่มีนิ้วบัง"
    },
    {
     "n": 5,
     "caption": "ลูกค้าถือเครื่องโชว์หน้าจอ \"เกี่ยวกับ\" (ถ่ายที่ศูนย์อาหารในห้าง) เห็นเวอร์ชั่น iOS 26.3 / ชื่อรุ่น iPhone 17 Pro / หมายเลขรุ่น MG8G4ZP/A / เลขประจำเครื่อง L562772N9H พร้อมเห็นหน้าลูกค้าในรูปเดียวกัน"
    },
    {
     "n": 6,
     "caption": "วางบัตรประชาชนทาบบนหน้าจอเครื่องที่เปิดหน้า \"เกี่ยวกับ\" โดยวางบัตรไว้ใต้แถวเลขประจำเครื่อง ถ่ายจากด้านบนให้อ่านได้ทั้งข้อมูลบัตรและเลขประจำเครื่อง L562772N9H ในรูปเดียว"
    },
    {
     "n": 7,
     "caption": "ลูกค้าถือบัตรประชาชนขึ้นมาข้างหน้าระดับไหล่ ถ่ายให้เห็นหน้าลูกค้าและหน้าบัตรชัดพร้อมกันในรูปเดียว"
    }
   ],
   "steps": [
    {
     "title": "ถ่ายบัตรประชาชนลูกค้า (ชุดเซ็นสัญญา)",
     "detail": "วางบัตรบนพื้นเรียบ (ในตัวอย่างวางบนคีย์บอร์ดโน้ตบุ๊ก) ถ่ายจากด้านบนให้เห็นเต็มใบ อ่านเลขบัตร ชื่อ-นามสกุล ที่อยู่ วันออกบัตร วันหมดอายุ และเห็นรูปหน้าชัด เลี่ยงมุมที่แสงสะท้อนฮอโลแกรมพาดทับเลขบัตร",
     "page": 1
    },
    {
     "title": "ถ่ายลูกค้าถือสัญญา + เครื่อง",
     "detail": "ให้ลูกค้าถือสัญญาเช่าซื้อโทรศัพท์มือถือที่เซ็นชื่อเรียบร้อยแล้วมือหนึ่ง อีกมือถือเครื่องเปิดหน้าจอ \"เกี่ยวกับ\" ถ่ายรูปเดียวให้เห็นทั้งหน้าลูกค้า ตัวสัญญา และหน้าจอเครื่อง",
     "page": 2
    },
    {
     "title": "ถ่ายด้านหลังเครื่อง",
     "detail": "ถอดเคสออก ถือเครื่องขึ้นมาถ่ายด้านหลังให้เห็นทั้งเครื่องและกล้องหลังชัด ไม่ให้นิ้วบังตัวเครื่องหรือกล้อง",
     "page": 3
    },
    {
     "title": "ถ่ายบัตรประชาชนเต็มใบ (ชุดบัตร ปชช)",
     "detail": "ถ่ายบัตรใบเดี่ยวบนพื้นเรียบให้เห็นเต็มใบ ตัวหนังสืออ่านออกทุกบรรทัด ไม่มีนิ้วบังและไม่มีแสงสะท้อนทับข้อมูล",
     "page": 4
    },
    {
     "title": "ถ่ายลูกค้าโชว์หน้าจอ \"เกี่ยวกับ\"",
     "detail": "เปิด ตั้งค่า > ทั่วไป > เกี่ยวกับ แล้วให้ลูกค้าถือเครื่องขึ้นมา ถ่ายให้เห็นหน้าลูกค้าคู่กับหน้าจอที่แสดง ชื่อรุ่น หมายเลขรุ่น และเลขประจำเครื่อง ครบในรูปเดียว",
     "page": 5
    },
    {
     "title": "ถ่ายบัตรทาบกับหน้าจอเครื่อง",
     "detail": "วางเครื่องที่เปิดหน้า \"เกี่ยวกับ\" ไว้บนโต๊ะ แล้ววางบัตรประชาชนทาบบนหน้าจอ โดยวางไว้ใต้แถวเลขประจำเครื่อง ไม่ให้บัตรทับแถว ชื่อรุ่น / หมายเลขรุ่น / เลขประจำเครื่อง ถ่ายจากด้านบนให้อ่านได้ทั้งบัตรและเลขเครื่องในรูปเดียว",
     "page": 6
    },
    {
     "title": "ถ่ายลูกค้าถือบัตรคู่กับหน้า",
     "detail": "ให้ลูกค้าถือบัตรประชาชนขึ้นมาข้างหน้าระดับไหล่ ถ่ายให้เห็นหน้าลูกค้าและหน้าบัตรชัดพร้อมกันในรูปเดียว",
     "page": 7
    }
   ],
   "warnings": [
    "รูปบัตรต้องเห็นเต็มใบ อ่านเลขบัตร 13 หลักและชื่อ-นามสกุลได้ครบ ระวังแสงสะท้อน/ฮอโลแกรมพาดทับแถวเลขบัตรแบบในรูป 1 และอย่าให้นิ้วบังข้อมูล",
    "ตอนวางบัตรทาบหน้าจอ (รูป 6) ต้องวางบัตรใต้แถวเลขประจำเครื่อง ห้ามให้บัตรทับแถว ชื่อรุ่น / หมายเลขรุ่น / เลขประจำเครื่อง ไม่งั้นรูปใช้ไม่ได้ ต้องถ่ายใหม่",
    "เลขประจำเครื่องในรูป 5 กับ รูป 6 ต้องเป็นเครื่องเดียวกันและตรงกัน (ตัวอย่างคือ L562772N9H ทั้งคู่) ถ้าไม่ตรงแปลว่าถ่ายคนละเครื่อง ใช้ไม่ได้",
    "รูปลูกค้าถือสัญญา (รูป 2) ต้องเห็นครบ 3 อย่างในรูปเดียว คือ หน้าลูกค้า ตัวสัญญาที่เซ็นแล้ว และหน้าจอเครื่อง ห้ามแยกถ่าย",
    "รูปที่ต้องเห็นหน้าลูกค้า (รูป 2, 5, 7) อย่าให้หน้าเบลอ มืด หรือมีแสงแฟลร์พาดจนดูไม่ออกว่าเป็นคนเดียวกับรูปในบัตร",
    "ตัวอย่างในคู่มือนี้เป็นลูกค้าคนละราย คนละเครื่อง (รูป 1-3 ถ่ายที่ออฟฟิศ, รูป 4-7 เป็นอีกรายถ่ายที่ห้าง) เวลาใช้งานจริงรูปทุกใบของลูกค้า 1 ราย ต้องเป็นคนเดียวกันและเครื่องเดียวกันทั้งชุด",
    "ชุดเซ็นสัญญาต้องครบ 3 ใบ (รูป 1-3) และชุดบัตร ปชช ต้องครบ 4 ใบ (รูป 4-7) ขาดใบไหนใบหนึ่งถือว่าชุดไม่สมบูรณ์ ต้องถ่ายเพิ่มให้ครบ"
   ]
  },
  {
   "slug": "check-device",
   "title": "SOP วิธีเช็กเครื่องลูกค้า",
   "subtitle": "ใช้ตอนลูกค้าเอา iPhone มาขาย/จำนำ ต้องเช็กสภาพเครื่องก่อนรับซื้อ",
   "icon": "🔍",
   "summary": "เช็กลิสต์ 6 ข้อสำหรับพนักงานหน้าร้าน ใช้ตรวจ iPhone ของลูกค้าก่อนรับซื้อ/รับจำนำ ครอบคลุมสุขภาพแบต ประเภทเครื่อง สถานะติดผ่อน/iCloud/MDM สภาพตัวเครื่อง อะไหล่ และ Parts & Service History ท้ายคู่มือมีรายการรูปที่ต้องให้ลูกค้าส่ง และตารางสรุปเงื่อนไขร้านว่าเคสไหนรับปกติ เคสไหนหักราคา เคสไหนไม่รับ",
   "keywords": [
    "เช็กเครื่องลูกค้า",
    "เช็คเครื่อง",
    "รับซื้อ iPhone",
    "รับจำนำ",
    "สุขภาพแบตเตอรี่",
    "battery health",
    "Model Number",
    "เครื่องไทย",
    "เครื่องนอก",
    "ติด iCloud",
    "ติด MDM",
    "Activation Lock",
    "Parts & Service History",
    "อะไหล่เทียบ Copy",
    "เงื่อนไขรับซื้อ"
   ],
   "pages": [
    {
     "n": 1,
     "caption": "โปสเตอร์ SOP วิธีเช็กเครื่องลูกค้า คอลัมน์ซ้ายเป็นเช็กลิสต์ 6 ข้อ (แบต / ประเภทเครื่อง / ติดผ่อน-iCloud-MDM / สภาพตัวเครื่อง / อะไหล่ / Parts & Service History) คอลัมน์ขวาเป็นรายการรูปที่ต้องให้ลูกค้าส่ง 9 รูป และกล่องสรุปเงื่อนไขร้าน รับปกติ-หักราคา-ไม่รับ"
    }
   ],
   "steps": [
    {
     "title": "เช็กสุขภาพแบตเตอรี่",
     "detail": "แบต 80-100% = รับปกติ / แบต 75-79% = หัก 500 บาท / แบตต่ำกว่า 75% = ไม่รับ",
     "page": 1
    },
    {
     "title": "เช็กประเภทเครื่อง",
     "detail": "เช็ก Model Number ถ้าเป็น TH/A หรือ ZP/A = เครื่องไทย ถ้าเป็น Model อื่น = เครื่องนอก หัก 1,000 บาท",
     "page": 1
    },
    {
     "title": "เช็กสถานะติดผ่อน / ติด iCloud / ติด MDM",
     "detail": "สอบถามว่าติดผ่อนหรือไม่ / ยอดติดทั้งหมดเท่าไหร่ / ติด iCloud หรือไม่ / ติด MDM หรือไม่ แล้วคำนวณหลังหักค่าบริการ ค่าปิด iCloud และส่วนต่าง 10% หากยอดไม่ผ่านเกณฑ์ร้าน = ไม่รับ",
     "page": 1
    },
    {
     "title": "เช็กสภาพตัวเครื่อง (ให้ลูกค้าถ่ายรูปส่งด้วย)",
     "detail": "เครื่องไม่งอ / จอไม่แตก / ฝาหลังไม่แตกหนัก / กระจกไม่แตกหนัก / กล้องไม่แตก / มีเพียงรอยใช้งานทั่วไป",
     "page": 1
    },
    {
     "title": "เช็กอะไหล่",
     "detail": "ถามว่ามีการเปลี่ยนอะไหล่หรือไม่ ไม่รับ: อะไหล่เทียบ (Copy) / เปลี่ยนอะไหล่ตั้งแต่ 3 รายการขึ้นไป / เปลี่ยน Logic Board (เมนบอร์ด) / Face ID เสีย ส่วนหักราคา: เปลี่ยนแบตเตอรี่ หัก 500 บาท / เปลี่ยนกล้อง หัก 500 บาท / อะไหล่อื่น หักตามเงื่อนไขร้าน",
     "page": 1
    },
    {
     "title": "เช็ก Parts & Service History",
     "detail": "เช็กประวัติการเปลี่ยนอะไหล่ในเครื่อง ทั้ง จอ / แบต / กล้อง / อะไหล่อื่น",
     "page": 1
    },
    {
     "title": "ขอรูปจากลูกค้าให้ครบ 9 รูป",
     "detail": "ด้านหน้า (เปิดหน้าจอ) / ด้านหลัง / ด้านบน / ด้านล่าง / ด้านซ้าย / ด้านขวา / รูปสุขภาพแบตเตอรี่ / รูป Model Number / รูป Parts & Service History (ถ้ามี)",
     "page": 1
    },
    {
     "title": "สรุปเงื่อนไขร้านก่อนตัดสินใจ",
     "detail": "รับปกติ: แบต 80% ขึ้นไป / เครื่องไทย / สภาพเครื่องปกติ / Face ID ใช้งานได้ / อะไหล่แท้หรือเปลี่ยนตามเงื่อนไขร้าน — หักราคา: แบต 75-79% หัก 500 / เครื่องนอก หัก 1,000 / เปลี่ยนแบต หัก 500 / เปลี่ยนกล้อง หัก 500 / อะไหล่อื่น หักตามเงื่อนไขร้าน — ไม่รับ: แบตต่ำกว่า 75% / เครื่องงอ / จอแตกหนัก / ฝาหลังแตกหนัก / กล้องแตก / Face ID เสีย / อะไหล่เทียบ (Copy) / เปลี่ยนอะไหล่ตั้งแต่ 3 รายการขึ้นไป / เปลี่ยน Logic Board / ติด Activation Lock / ติด MDM / ยอดติดผ่อน-ติด iCloud ไม่ผ่านเกณฑ์ร้าน / IMEI ติด Blacklist หรือเป็นเครื่องแจ้งสูญหาย",
     "page": 1
    }
   ],
   "warnings": [
    "แบตต่ำกว่า 75% = ไม่รับ ส่วน 75-79% รับได้แต่หัก 500 บาท อย่าจำสลับกัน",
    "Model Number ต้องดูให้ชัด มีแค่ TH/A กับ ZP/A ที่เป็นเครื่องไทย นอกนั้นเป็นเครื่องนอก หัก 1,000 บาท",
    "เครื่องที่ติด Activation Lock หรือติด MDM = ไม่รับ",
    "ยอดติดผ่อน/ติด iCloud ต้องคำนวณหลังหักค่าบริการ ค่าปิด iCloud และส่วนต่าง 10% ก่อน ถ้ายอดไม่ผ่านเกณฑ์ร้าน = ไม่รับ",
    "IMEI ติด Blacklist หรือเป็นเครื่องแจ้งสูญหาย = ไม่รับ",
    "เปลี่ยนอะไหล่ตั้งแต่ 3 รายการขึ้นไป หรือเปลี่ยน Logic Board = ไม่รับ",
    "อะไหล่เทียบ (Copy) และ Face ID เสีย = ไม่รับ (รับปกติต้อง Face ID ใช้งานได้ และอะไหล่แท้หรือเปลี่ยนตามเงื่อนไขร้าน)",
    "สภาพเครื่องที่ไม่รับ: เครื่องงอ / จอแตกหนัก / ฝาหลังแตกหนัก / กล้องแตก — รอยใช้งานทั่วไปรับได้",
    "รูปด้านซ้ายกับด้านขวาต้องถ่ายแยกกันคนละใบ ในรูปโปสเตอร์พิมพ์ตกเป็น \"ด้านข้าย\" แต่หมายถึงด้านซ้าย",
    "หมายเหตุท้ายคู่มือ: การตัดสินใจรับซื้อเครื่องเป็นไปตามเงื่อนไขของทางร้านเท่านั้น พนักงานมีสิทธิ์ปฏิเสธการรับซื้อ หากไม่เป็นไปตามเงื่อนไขข้างต้น"
   ]
  },
  {
   "slug": "staff",
   "title": "คู่มือพนักงาน ตอบแชท LINE OA",
   "subtitle": "ใช้ทุกครั้งที่ลูกค้าทักเข้ามาใน LINE OA ตั้งแต่สอบถามข้อมูลจนถึงนัดทำสัญญา",
   "icon": "💬",
   "summary": "คู่มือ SOP ขั้นตอนการตอบแชทลูกค้าทาง LINE OA 10 ขั้นตอน ตั้งแต่สอบถามข้อมูล แคปหน้าจอ แจ้งราคารับซื้อ แจ้งรายละเอียดค่าบริการ ไปจนถึงรอลูกค้าแจ้งกลับ พร้อมวิธีการทำสัญญา 3 รูปแบบ (ออนไลน์ / หน้าร้าน / นอกสถานที่) สำหรับพนักงานที่ตอบแชทลูกค้า เพื่อให้ทุกคนตอบเป็นมาตรฐานเดียวกัน ดำเนินการครบทุกขั้นตอน และไม่ตกหล่นระหว่างการให้บริการ",
   "keywords": [
    "ตอบแชท",
    "LINE OA",
    "คู่มือพนักงาน",
    "SOP",
    "แจ้งราคารับซื้อ",
    "ค่าบริการติดตั้ง MDM",
    "ทำสัญญาออนไลน์",
    "ทำสัญญาหน้าร้าน",
    "นอกสถานที่",
    "Delivery",
    "สำรองข้อมูล",
    "เอกสารทำสัญญา",
    "ขอข้อมูลลูกค้า",
    "chat",
    "staff manual"
   ],
   "pages": [
    {
     "n": 1,
     "caption": "อินโฟกราฟิกคู่มือพนักงาน ขั้นตอนการตอบแชท LINE OA (SOP) ทั้งใบ — วัตถุประสงค์, 10 ขั้นตอนการตอบแชท, วิธีการทำสัญญา 3 รูปแบบ และหมายเหตุ (ใบนี้อ่านกล่องตัวอย่างของขั้นตอนที่ 4 ได้ชัดที่สุด)"
    },
    {
     "n": 2,
     "caption": "อินโฟกราฟิกใบเดียวกัน อีกเวอร์ชันหนึ่ง เนื้อหาและเลย์เอาต์เหมือนกันทุกส่วน ตัวหนังสือส่วนหัวข้อและช่องวิธีทำสัญญาอ่านชัดกว่า"
    }
   ],
   "steps": [
    {
     "title": "สอบถามข้อมูลลูกค้า (สอบถาม)",
     "detail": "สอบถามข้อมูลให้ครบถ้วน เพื่อเข้าใจความต้องการของลูกค้า",
     "page": 2
    },
    {
     "title": "แคปหน้าจอข้อมูลลูกค้า (แคปจอ)",
     "detail": "แคปหน้าจอข้อมูลลูกค้าสำคัญเก็บไว้",
     "page": 2
    },
    {
     "title": "แจ้งราคารับซื้อ (ราคา)",
     "detail": "แจ้งราคาให้ลูกค้าทราบ ตามตัวอย่างในรูป: ร้านรับอยู่ 12,000 บาท / มีค่าบริการทำสัญญาและติดตั้งระบบความปลอดภัย 400 บาท / ยอดที่ลูกค้าจะได้รับสุทธิ = 11,600 บาทครับ",
     "page": 2
    },
    {
     "title": "แจ้งรายละเอียดการชำระค่าบริการ (แจ้ง)",
     "detail": "ตามตัวอย่างในรูป: ในการชำระค่าเช่าบริการ / หากยอดรับซื้อ 20,000 บาท / ค่าบริการอยู่ที่ 10% / ลูกค้าจะชำระ 2,000 บาท ทุก ๆ 10 วัน / ลูกค้าสามารถชำระได้เรื่อย ๆ จนกว่าจะปิดยอด 22,000 บาท / หากลูกค้าไม่ต้องการปิดยอดทั้งหมดในครั้งเดียว สามารถตัดเงินต้นได้ตั้งแต่รอบบิลที่ 2 เป็นต้นไป ขั้นต่ำ 500 บาท",
     "page": 1
    },
    {
     "title": "สอบถามว่าลูกค้าเข้าใจรายละเอียดหรือไม่ (เข้าใจ)",
     "detail": "ตรวจสอบความเข้าใจของลูกค้าอีกครั้ง ก่อนไปขั้นตอนถัดไป",
     "page": 2
    },
    {
     "title": "ส่งรายละเอียดการรับซื้อเครื่อง (ราย)",
     "detail": "ส่งรายละเอียดการรับซื้อเครื่องให้ลูกค้า",
     "page": 2
    },
    {
     "title": "ส่งรายละเอียดค่าบริการติดตั้ง MDM (ค่า)",
     "detail": "ส่งรายละเอียดค่าบริการติดตั้ง MDM ให้ลูกค้า",
     "page": 2
    },
    {
     "title": "ส่งรายการเอกสารที่ใช้ในการทำสัญญา (เอกสาร)",
     "detail": "ส่งรายการเอกสารที่ใช้ในการทำสัญญาให้ลูกค้า",
     "page": 2
    },
    {
     "title": "แจ้งวิธีการทำสัญญา 3 รูปแบบ (สัญญา)",
     "detail": "แจ้งวิธีการทำสัญญาให้ลูกค้าเลือก 3 รูปแบบ คือ ทำสัญญาออนไลน์ / มาทำสัญญาที่หน้าร้าน / ให้บริการนอกสถานที่",
     "page": 2
    },
    {
     "title": "รอลูกค้าแจ้งกลับเพื่อดำเนินการต่อ",
     "detail": "เมื่อครบทุกขั้นตอนแล้ว รอลูกค้าแจ้งกลับ",
     "page": 2
    },
    {
     "title": "วิธีทำสัญญาแบบที่ 1 — กรณีทำสัญญาออนไลน์ (ออนไลน์)",
     "detail": "สอบถามว่าลูกค้าเตรียมเอกสารพร้อมไหม → หากครบ ให้ลูกค้าเตรียมเครื่องให้พร้อม → ส่งนัดแนะนำก่อนทำสัญญา (ข้อความ/วิดีโอ) → ส่ง 3 รูป → ส่งวิธีสำรองข้อมูล (สำรอง) → แจ้งลูกค้าว่า เมื่อดำเนินการเสร็จแล้ว ระบบจะแนบลิงก์ในขั้นตอนตรวจสอบนะคะ → ขอข้อมูลทั้งหมด (ขอข้อมูล) → เมื่อลูกค้าเตรียมเครื่องและส่งข้อมูลครบแล้ว จึงนัดเวลาทำสัญญาออนไลน์",
     "page": 2
    },
    {
     "title": "วิธีทำสัญญาแบบที่ 2 — กรณีมาทำสัญญาที่หน้าร้าน",
     "detail": "ส่งนัดแนะนำก่อนทำสัญญา (ข้อความ/วิดีโอ) → ส่ง 3 รูป → ส่งวิธีสำรองข้อมูล (สำรอง) → แจ้งลูกค้าว่า เมื่อดำเนินการเสร็จแล้ว ระบบจะแนบลิงก์ในขั้นตอนตรวจสอบนะคะ → ขอข้อมูลทั้งหมด (ขอข้อมูล) → เมื่อลูกค้าเตรียมเครื่องและส่งข้อมูลครบแล้ว จึงนัดวันและเวลามาหน้าร้าน",
     "page": 2
    },
    {
     "title": "วิธีทำสัญญาแบบที่ 3 — กรณีให้บริการนอกสถานที่",
     "detail": "ส่งรายละเอียด Delivery (Delivery) → ให้ลูกค้าส่งหมุดสถานที่ พร้อมวันและเวลาที่สะดวก → ติดต่อแอดมินเพื่อขอราคา → แจ้งค่าบริการนอกสถานที่ให้ลูกค้าทราบ และรอการยืนยัน → ส่งนัดแนะนำก่อนทำสัญญา (ข้อความ/วิดีโอ) → ส่ง 3 รูป → ส่งวิธีสำรองข้อมูล (สำรอง) → แจ้งลูกค้าว่า เมื่อดำเนินการเสร็จแล้ว ระบบจะแนบลิงก์ในขั้นตอนตรวจสอบนะคะ → ขอข้อมูลทั้งหมด (ขอข้อมูล) → เมื่อลูกค้าเตรียมเครื่องและส่งข้อมูลครบแล้ว จึงนัดเวลาร่วมกันนอกสถานที่",
     "page": 2
    }
   ],
   "warnings": [
    "ให้ดำเนินการตามลำดับขั้นตอนทุกครั้ง",
    "ห้ามข้ามขั้นตอน",
    "ใช้ข้อความมาตรฐานตามคู่มือในการตอบลูกค้า",
    "หากพบกรณีพิเศษหรือมีข้อมูลลับ ให้สอบถามหัวหน้าก่อนดำเนินการต่อ",
    "ทุกเคสต้องตรวจสอบให้ครบทั้ง 10 ขั้นตอน ก่อนปิดการสนทนา เพื่อป้องกันข้อมูลตกหล่นและรักษามาตรฐานการบริการ"
   ]
  }
 ],
 "tax": {
  "categories": [
   {
    "id": "intake",
    "name": "รับเคส & เช็กเครื่อง",
    "slugs": [
     "staff",
     "check-device"
    ]
   },
   {
    "id": "enroll",
    "name": "เข้าระบบ MDM & ทำสัญญา",
    "slugs": [
     "scan-atom",
     "mass-contract",
     "mdm-agent",
     "mass-mdm",
     "bypass-plus"
    ]
   },
   {
    "id": "lock",
    "name": "ล็อค–ปลดล็อค–ปิดสัญญา",
    "slugs": [
     "marena-lock"
    ]
   },
   {
    "id": "service",
    "name": "บริการลูกค้า",
    "slugs": [
     "line-payment",
     "line-backup"
    ]
   }
  ],
  "order": [
   "staff",
   "marena-lock",
   "check-device",
   "scan-atom",
   "line-payment",
   "mass-contract",
   "mdm-agent",
   "mass-mdm",
   "line-backup",
   "bypass-plus"
  ],
  "siteTitle": "คู่มือหน้าร้าน Thunder",
  "siteSubtitle": "รวมคู่มือ SOP ทุกขั้นตอน เปิดดูจากมือถือได้ทันที"
 }
}